{
	"types" : [
"1"
	],
	"alphabet" : [
"infoD|http(s)",
"CnC|http(s)",
"serD|unassigned",
"vulnD|storage",
"hostD|remoteAccess",
"surf|remoteAccess",
"infoD|remoteAccess",
"hostD|http(s)",
"surf|http(s)",
"netDOS|http(s)",
"hostD|surveillance",
"surf|surveillance",
"infoD|surveillance",
"bfCred|unassigned",
"hostD|hostingServer",
"surf|hostingServer",
"infoD|hostingServer",
"hostD|unassigned",
"rPrivEsc|http(s)",
"acctManip|http(s)",
"remoteexp|http(s)",
"ACE|http(s)",
"resHJ|http(s)",
"dManip|http(s)",
"exfil|http(s)",
"delivery|http(s)",
"vulnD|http(s)",
"vulnD|wireless",
"vulnD|surveillance",
"rPrivEsc|surveillance",
"remoteexp|surveillance",
"ACE|surveillance",
"dManip|surveillance",
"exfil|surveillance",
"serD|voip",
"vulnD|remoteAccess",
"infoD|unassigned",
"exfil|unassigned",
"serD|remoteAccess",
"uPrivEsc|http(s)",
"PAexp|http(s)",
"uPrivEsc|surveillance",
"delivery|surveillance",
"remoteexp|hostingServer",
"delivery|wireless",
"TOexp|http(s)",
"privEsc|http(s)",
"uPrivEsc|hostingServer",
"rPrivEsc|hostingServer",
"exfil|hostingServer",
"ACE|hostingServer",
"bfCred|email",
"acctManip|broadcast",
"netDOS|broadcast",
"hostD|wireless",
"rPrivEsc|email",
"surf|broadcast",
"infoD|broadcast",
"serD|surveillance",
"vulnD|voip",
"rPrivEsc|remoteAccess",
"acctManip|remoteAccess",
"remoteexp|remoteAccess",
"ACE|remoteAccess",
"resHJ|remoteAccess",
"dManip|remoteAccess",
"exfil|remoteAccess",
"delivery|remoteAccess",
"surf|wireless",
"infoD|wireless",
"rPrivEsc|wireless",
"acctManip|wireless",
"remoteexp|wireless",
"ACE|wireless",
"resHJ|wireless",
"dManip|wireless",
"exfil|wireless",
"surf|unassigned",
"vulnD|unassigned",
"rPrivEsc|unassigned",
"acctManip|unassigned",
"remoteexp|unassigned",
"ACE|unassigned",
"resHJ|unassigned",
"dManip|unassigned",
"delivery|unassigned",
"vulnD|hostingServer",
"acctManip|hostingServer",
"resHJ|hostingServer",
"dManip|hostingServer",
"acctManip|surveillance",
"resHJ|surveillance",
"serD|ATCcomm",
"CnC|unassigned",
"exfil|broadcast",
"CnC|surveillance",
"vulnD|broadcast",
"rPrivEsc|broadcast",
"remoteexp|broadcast",
"ACE|broadcast",
"resHJ|broadcast",
"dManip|broadcast",
"delivery|broadcast",
"dDestruct|remoteAccess",
"serD|storage",
"infoD|nameserver",
"serD|broadcast",
"delivery|hostingServer"
	],
	"nodes" : [
		{
			"id" : 0,
			"source" :  -1,
			"label" : " 427 0",
			"size" : 427,
			"level" : 0,
			"style" : "",
			"isred" :  1,
			"issink" :  0,
			"isblue" :  0,
			"data" :  {"path_counts":{"0":427},"total_final":0,"total_paths":427,"trans_counts":{"1":{"CnC|http(s)":1,"CnC|unassigned":1,"acctManip|broadcast":5,"exfil|remoteAccess":1,"hostD|hostingServer":10,"hostD|http(s)":41,"hostD|remoteAccess":15,"hostD|surveillance":6,"hostD|unassigned":6,"hostD|wireless":2,"infoD|http(s)":20,"infoD|nameserver":4,"infoD|surveillance":1,"infoD|unassigned":10,"rPrivEsc|http(s)":3,"serD|ATCcomm":2,"serD|remoteAccess":29,"serD|storage":1,"serD|surveillance":1,"serD|unassigned":181,"surf|hostingServer":2,"surf|http(s)":30,"surf|remoteAccess":4,"uPrivEsc|hostingServer":2,"vulnD|http(s)":7,"vulnD|remoteAccess":7,"vulnD|storage":35}}},
			"traces" : [ 426,425,424,423,422,421,420,419,418,417,416,415,414,413,412,411,410,409,408,407,406,405,404,403,402,401,400,399,398,397,396,395,394,393,392,391,390,389,388,387,386,385,384,383,382,381,380,379,378,377,376,375,374,373,372,371,370,369,368,367,366,365,364,363,362,361,360,359,358,357,356,355,354,353,352,351,350,349,348,347,346,345,344,343,342,341,340,339,338,337,336,335,334,333,332,331,330,329,328,327,326,325,324,323,322,321,320,319,318,317,316,315,314,313,312,311,310,309,308,307,306,305,304,303,302,301,300,299,298,297,296,295,294,293,292,291,290,289,288,287,286,285,284,283,282,281,280,279,278,277,276,275,274,273,272,271,270,269,268,267,266,265,264,263,262,261,260,259,258,257,256,255,254,253,252,251,250,249,248,247,246,245,244,243,242,241,240,239,238,237,236,235,234,233,232,231,230,229,228,227,226,225,224,223,222,221,220,219,218,217,216,215,214,213,212,211,210,209,208,207,206,205,204,203,202,201,200,199,198,197,196,195,194,193,192,191,190,189,188,187,186,185,184,183,182,181,180,179,178,177,176,175,174,173,172,171,170,169,168,167,166,165,164,163,162,161,160,159,158,157,156,155,154,153,152,151,150,149,148,147,146,145,144,143,142,141,140,139,138,137,136,135,134,133,132,131,130,129,128,127,126,125,124,123,122,121,120,119,118,117,116,115,114,113,112,111,110,109,108,107,106,105,104,103,102,101,100,99,98,97,96,95,94,93,92,91,90,89,88,87,86,85,84,83,82,81,80,79,78,77,76,75,74,73,72,71,70,69,68,67,66,65,64,63,62,61,60,59,58,57,56,55,54,53,52,51,50,49,48,47,46,45,44,43,42,41,40,39,38,37,36,35,34,33,32,31,30,29,28,27,26,25,24,23,22,21,20,19,18,17,16,15,14,13,12,11,10,9,8,7,6,5,4,3,2,1,0]
		},
		{
			"id" : 1,
			"source" :  0,
			"label" : " 36 0",
			"size" : 36,
			"level" : 2,
			"style" : "",
			"isred" :  1,
			"issink" :  0,
			"isblue" :  0,
			"data" :  {"final_counts":{"0":0},"path_counts":{"0":36},"total_final":0,"total_paths":36,"trans_counts":{"1":{"hostD|hostingServer":1,"infoD|http(s)":4,"netDOS|http(s)":15,"rPrivEsc|http(s)":0,"remoteexp|http(s)":2,"serD|surveillance":1,"serD|unassigned":1,"surf|http(s)":11,"uPrivEsc|hostingServer":1}}},
			"traces" : [ 393,390,318,317,316,315,314,309,308,306,304,303,302,269,245,219,158,146,145,0,285,416,423,388,319,124,120,7,327,104,103,411,392,288,297,5]
		},
		{
			"id" : 3,
			"source" :  0,
			"label" : " 463 1",
			"size" : 464,
			"level" : 10,
			"style" : "",
			"isred" :  1,
			"issink" :  0,
			"isblue" :  0,
			"data" :  {"final_counts":{"0":1},"path_counts":{"0":463},"total_final":1,"total_paths":463,"trans_counts":{"1":{"CnC|http(s)":1,"bfCred|email":1,"hostD|hostingServer":0,"hostD|http(s)":0,"hostD|remoteAccess":0,"hostD|surveillance":0,"infoD|unassigned":1,"serD|broadcast":1,"serD|storage":1,"serD|unassigned":7,"vulnD|http(s)":1,"vulnD|remoteAccess":4,"vulnD|storage":446}}},
			"traces" : [ 425,419,418,414,400,399,398,397,395,394,391,386,385,382,377,375,359,345,342,340,334,332,331,330,328,327,326,324,323,322,297,296,295,294,293,287,283,282,281,276,275,274,270,268,266,265,262,261,260,259,257,250,249,248,247,246,244,240,239,237,236,226,224,217,216,215,214,213,212,211,210,199,190,189,188,187,186,185,184,183,177,176,175,174,171,169,168,167,166,157,155,154,153,152,151,150,149,148,144,143,140,139,138,137,136,135,134,133,130,129,128,127,126,125,117,116,115,114,113,112,111,110,109,108,107,106,104,103,102,101,98,96,95,94,93,92,87,86,85,84,70,69,64,60,56,55,54,53,50,49,46,45,44,43,40,39,36,35,33,32,31,30,29,28,27,26,25,24,23,22,21,20,19,18,17,14,6,5,4,3,1,362,362,362,362,362,381,381,381,378,378,381,234,389,234,389,383,234,342,409,147,147,156,147,154,150,134,172,172,285,172,163,42,15,173,173,160,97,37,9,339,339,340,50,49,17,339,342,339,371,337,337,347,339,125,128,127,126,371,337,373,178,178,416,278,178,162,119,13,12,73,32,177,176,175,174,168,167,166,117,244,134,117,116,342,130,262,130,179,288,179,165,141,91,34,413,411,403,402,401,392,288,277,273,222,205,191,179,170,165,164,161,159,141,132,118,99,91,71,52,51,41,34,11,10,8,137,188,185,154,150,137,115,114,113,112,111,110,31,6,377,275,259,189,188,185,184,183,177,176,175,174,169,168,167,166,155,154,153,152,151,150,149,148,137,133,126,116,115,114,113,112,111,110,31,30,28,27,26,25,24,23,6,5,4,3,425,418,398,395,394,391,377,297,296,295,294,293,281,276,275,268,265,260,259,249,247,246,239,237,217,215,213,212,211,210,190,189,188,187,186,185,184,183,177,176,175,174,171,169,168,167,166,155,154,153,152,151,150,149,148,139,138,137,135,133,130,128,127,126,117,116,115,114,113,112,111,110,96,92,46,44,43,39,36,35,33,31,30,28,27,26,25,24,23,21,20,19,14,6,5,4,3,1]
		},
		{
			"id" : 4,
			"source" :  0,
			"label" : " 174 4",
			"size" : 178,
			"level" : 3,
			"style" : "",
			"isred" :  1,
			"issink" :  0,
			"isblue" :  0,
			"data" :  {"final_counts":{"0":4},"path_counts":{"0":174},"total_final":4,"total_paths":174,"trans_counts":{"1":{"CnC|http(s)":0,"acctManip|broadcast":4,"exfil|unassigned":3,"hostD|hostingServer":0,"hostD|http(s)":3,"hostD|remoteAccess":3,"hostD|surveillance":0,"hostD|unassigned":0,"hostD|wireless":1,"infoD|http(s)":0,"infoD|nameserver":1,"infoD|remoteAccess":0,"infoD|unassigned":0,"rPrivEsc|http(s)":0,"serD|ATCcomm":2,"serD|broadcast":1,"serD|remoteAccess":1,"serD|storage":2,"serD|surveillance":2,"serD|unassigned":39,"surf|hostingServer":0,"surf|http(s)":0,"surf|surveillance":0,"vulnD|remoteAccess":20,"vulnD|storage":92}}},
			"traces" : [ 381,380,378,376,373,368,366,365,364,363,362,360,357,355,354,353,351,350,349,348,347,346,344,343,339,338,336,335,263,218,90,89,88,48,38,344,344,344,362,344,362,344,340,340,340,379,379,374,374,360,374,366,374,360,368,366,355,374,358,368,360,352,352,352,352,352,352,380,366,355,374,358,352,368,360,346,365,365,346,365,380,366,355,379,374,369,358,352,365,368,360,346,357,373,373,373,373,357,338,381,381,381,338,373,364,348,344,338,381,357,353,353,363,363,363,363,353,365,363,353,348,344,338,381,376,357,335,373,364,354,336,378,353,348,378,353,348,378,353,348,344,338,381,378,376,362,360,357,353,349,348,346,344,343,338,335,218,381,378,376,373,368,364,362,360,357,354,353,350,349,348,346,344,343,338,336,335,218]
		},
		{
			"id" : 6,
			"source" :  0,
			"label" : " 59 6",
			"size" : 65,
			"level" : 2,
			"style" : "",
			"isred" :  1,
			"issink" :  0,
			"isblue" :  0,
			"data" :  {"final_counts":{"0":6},"path_counts":{"0":59},"total_final":6,"total_paths":59,"trans_counts":{"1":{"bfCred|email":1,"hostD|http(s)":4,"infoD|http(s)":0,"infoD|remoteAccess":2,"serD|remoteAccess":13,"serD|unassigned":36,"vulnD|http(s)":3,"vulnD|storage":0}}},
			"traces" : [ 424,421,413,411,403,402,401,392,288,277,273,242,228,227,225,223,222,221,220,205,191,179,170,165,164,161,159,141,132,118,100,99,91,71,52,51,41,34,11,10,8,381,383,125,32,166,244,331,330,244,224,140,134,56,53,287,130,165,141,91,34,179,395,117,116]
		},
		{
			"id" : 7,
			"source" :  0,
			"label" : " 54 1",
			"size" : 55,
			"level" : 3,
			"style" : "",
			"isred" :  1,
			"issink" :  0,
			"isblue" :  0,
			"data" :  {"final_counts":{"0":1},"path_counts":{"0":54},"total_final":1,"total_paths":54,"trans_counts":{"1":{"CnC|http(s)":4,"hostD|http(s)":12,"infoD|http(s)":16,"infoD|unassigned":5,"rPrivEsc|http(s)":2,"rPrivEsc|remoteAccess":1,"serD|remoteAccess":1,"serD|unassigned":2,"vulnD|http(s)":10,"vulnD|wireless":1}}},
			"traces" : [ 423,388,321,320,319,313,311,310,301,299,289,286,267,241,207,204,203,202,201,200,196,194,193,181,180,124,120,72,16,7,285,17,416,13,327,322,104,103,18,411,392,288,297,5,318,317,316,315,314,309,308,306,304,303,302]
		},
		{
			"id" : 8,
			"source" :  0,
			"label" : " 6 0",
			"size" : 6,
			"level" : 1,
			"style" : "",
			"isred" :  1,
			"issink" :  0,
			"isblue" :  0,
			"data" :  {"path_counts":{"0":6},"total_final":0,"total_paths":6,"trans_counts":{"1":{"serD|surveillance":1,"serD|unassigned":5}}},
			"traces" : [ 271,173,160,97,37,9]
		},
		{
			"id" : 10,
			"source" :  0,
			"label" : " 10 0",
			"size" : 10,
			"level" : 1,
			"style" : "",
			"isred" :  1,
			"issink" :  0,
			"isblue" :  0,
			"data" :  {"path_counts":{"0":10},"total_final":0,"total_paths":10,"trans_counts":{"1":{"infoD|hostingServer":1,"serD|remoteAccess":1,"serD|unassigned":7,"surf|hostingServer":1}}},
			"traces" : [ 416,278,208,197,178,162,131,119,13,12]
		},
		{
			"id" : 12,
			"source" :  0,
			"label" : " 6 0",
			"size" : 6,
			"level" : 1,
			"style" : "",
			"isred" :  1,
			"issink" :  0,
			"isblue" :  0,
			"data" :  {"path_counts":{"0":6},"total_final":0,"total_paths":6,"trans_counts":{"1":{"serD|unassigned":5,"surf|unassigned":1}}},
			"traces" : [ 285,195,172,163,42,15]
		},
		{
			"id" : 14,
			"source" :  0,
			"label" : " 7 0",
			"size" : 7,
			"level" : 1,
			"style" : "",
			"isred" :  1,
			"issink" :  0,
			"isblue" :  0,
			"data" :  {"final_counts":{"0":0},"path_counts":{"0":7},"total_final":0,"total_paths":7,"trans_counts":{"1":{"acctManip|http(s)":1,"dManip|http(s)":1,"rPrivEsc|hostingServer":1,"rPrivEsc|http(s)":3,"serD|remoteAccess":1}}},
			"traces" : [ 422,417,298,290,66,63,47]
		},
		{
			"id" : 15,
			"source" :  0,
			"label" : " 20 2",
			"size" : 22,
			"level" : 2,
			"style" : "",
			"isred" :  1,
			"issink" :  0,
			"isblue" :  0,
			"data" :  {"final_counts":{"0":2},"path_counts":{"0":20},"total_final":2,"total_paths":20,"trans_counts":{"1":{"CnC|http(s)":0,"dDestruct|remoteAccess":1,"exfil|unassigned":5,"hostD|http(s)":1,"infoD|unassigned":3,"rPrivEsc|http(s)":4,"serD|unassigned":5,"uPrivEsc|hostingServer":1}}},
			"traces" : [ 312,307,305,300,272,264,238,156,147,142,154,97,37,261,257,143,134,117,273,237,154,150]
		},
		{
			"id" : 16,
			"source" :  0,
			"label" : " 68 6",
			"size" : 74,
			"level" : 3,
			"style" : "",
			"isred" :  1,
			"issink" :  0,
			"isblue" :  0,
			"data" :  {"final_counts":{"0":6},"path_counts":{"0":68},"total_final":6,"total_paths":68,"trans_counts":{"1":{"CnC|http(s)":1,"PAexp|http(s)":3,"bfCred|unassigned":2,"hostD|http(s)":4,"rPrivEsc|email":1,"serD|remoteAccess":20,"serD|unassigned":6,"surf|http(s)":2,"vulnD|http(s)":4,"vulnD|storage":25}}},
			"traces" : [ 415,410,409,408,407,405,396,389,387,384,383,367,235,234,233,232,231,230,229,198,123,121,68,67,65,62,59,58,57,234,234,342,339,400,399,136,60,126,128,127,402,125,424,421,242,228,227,225,223,221,220,224,56,130,410,408,407,198,68,67,410,409,408,407,235,233,232,231,230,229,198,68,67,59]
		},
		{
			"id" : 18,
			"source" :  0,
			"label" : " 5 0",
			"size" : 5,
			"level" : 1,
			"style" : "",
			"isred" :  1,
			"issink" :  0,
			"isblue" :  0,
			"data" :  {"final_counts":{"0":0},"path_counts":{"0":5},"total_final":0,"total_paths":5,"trans_counts":{"1":{"serD|unassigned":5}}},
			"traces" : [ 256,254,253,252,251]
		},
		{
			"id" : 28,
			"source" :  1,
			"label" : " 2 13",
			"size" : 15,
			"level" : 3,
			"style" : "",
			"isred" :  1,
			"issink" :  0,
			"isblue" :  0,
			"data" :  {"final_counts":{"0":13},"path_counts":{"0":2},"total_final":13,"total_paths":2,"trans_counts":{"1":{"resHJ|http(s)":2}}},
			"traces" : [ 245,285,416,423,388,319,124,7,327,104,103,411,288,297,5]
		},
		{
			"id" : 35,
			"source" :  3,
			"label" : " 386 104",
			"size" : 490,
			"level" : 11,
			"style" : "",
			"isred" :  1,
			"issink" :  0,
			"isblue" :  0,
			"data" :  {"final_counts":{"0":104},"path_counts":{"0":386},"total_final":104,"total_paths":386,"trans_counts":{"1":{"CnC|http(s)":1,"CnC|surveillance":1,"acctManip|broadcast":2,"bfCred|email":5,"bfCred|unassigned":5,"exfil|broadcast":2,"exfil|remoteAccess":1,"hostD|hostingServer":3,"hostD|http(s)":24,"hostD|remoteAccess":17,"hostD|surveillance":4,"hostD|unassigned":2,"hostD|wireless":4,"infoD|http(s)":2,"infoD|remoteAccess":12,"infoD|unassigned":12,"rPrivEsc|http(s)":2,"serD|broadcast":1,"serD|remoteAccess":12,"serD|surveillance":2,"serD|unassigned":189,"serD|voip":3,"surf|broadcast":3,"surf|hostingServer":1,"surf|http(s)":14,"surf|surveillance":2,"uPrivEsc|hostingServer":3,"vulnD|http(s)":2,"vulnD|remoteAccess":10,"vulnD|storage":44,"vulnD|voip":1}}},
			"traces" : [ 425,419,418,414,400,399,398,397,395,394,391,385,382,377,359,342,334,332,331,330,328,327,326,324,322,297,296,295,294,293,287,283,282,281,276,275,274,270,268,265,262,261,260,259,257,250,249,248,247,246,244,240,239,237,236,226,224,217,216,215,214,213,212,211,210,199,190,189,188,187,186,185,184,183,177,176,175,174,171,169,168,167,166,157,155,154,153,152,151,150,149,148,144,143,140,139,138,137,136,135,134,133,130,129,128,127,126,125,117,116,115,114,113,112,111,110,109,108,107,106,104,103,102,101,98,96,95,94,93,92,87,86,85,84,70,69,64,60,56,55,54,53,46,45,44,43,40,39,36,35,33,32,31,30,29,28,27,26,25,24,23,22,21,20,19,18,14,6,5,4,3,1,362,362,362,362,362,362,362,381,381,381,381,381,381,342,234,389,234,389,383,234,342,409,147,147,156,147,154,150,134,172,172,285,172,163,42,15,173,173,173,160,97,37,9,339,339,339,340,339,342,340,50,49,17,339,342,339,339,371,371,339,371,339,371,373,337,337,337,337,347,339,125,128,127,126,371,337,373,178,178,416,278,178,162,119,13,12,176,73,32,177,176,175,174,168,167,166,117,244,134,117,342,359,342,359,342,130,130,359,342,334,326,287,274,262,125,69,55,45,130,128,127,377,126,179,288,179,165,141,91,34,413,411,403,402,401,392,288,277,273,222,205,191,179,170,165,164,161,159,141,132,118,99,91,71,52,51,41,34,11,10,8,137,188,185,154,150,137,115,114,113,112,111,110,31,6,377,275,259,189,188,185,184,183,177,176,175,174,169,168,167,166,155,154,153,152,151,150,149,148,137,133,126,116,115,114,113,112,111,110,31,30,28,27,26,25,24,23,6,5,4,3,425,398,395,394,391,377,297,296,295,294,293,281,276,275,268,265,260,259,249,247,246,239,237,217,215,213,212,211,210,190,189,188,187,186,185,184,183,177,176,175,174,171,169,168,167,166,155,154,153,152,151,150,149,148,139,138,137,135,133,130,128,127,126,117,116,115,114,113,112,111,110,96,92,46,44,43,39,36,35,33,31,30,28,27,26,25,24,23,21,20,19,14,6,5,4,3,1]
		},
		{
			"id" : 42,
			"source" :  4,
			"label" : " 39 0",
			"size" : 39,
			"level" : 4,
			"style" : "",
			"isred" :  1,
			"issink" :  0,
			"isblue" :  0,
			"data" :  {"final_counts":{"0":0},"path_counts":{"0":39},"total_final":0,"total_paths":39,"trans_counts":{"1":{"bfCred|email":0,"hostD|hostingServer":1,"hostD|http(s)":0,"hostD|remoteAccess":0,"hostD|surveillance":1,"serD|storage":0,"serD|surveillance":1,"serD|unassigned":1,"vulnD|http(s)":0,"vulnD|remoteAccess":5,"vulnD|storage":30}}},
			"traces" : [ 365,363,48,38,379,374,368,352,352,352,352,346,346,365,373,373,338,381,381,381,344,338,363,363,353,378,353,348,344,338,381,376,362,357,335,373,364,354,336]
		},
		{
			"id" : 45,
			"source" :  4,
			"label" : " 41 1",
			"size" : 42,
			"level" : 7,
			"style" : "",
			"isred" :  1,
			"issink" :  0,
			"isblue" :  0,
			"data" :  {"final_counts":{"0":1},"path_counts":{"0":41},"total_final":1,"total_paths":41,"trans_counts":{"1":{"acctManip|broadcast":3,"infoD|nameserver":1,"serD|remoteAccess":1,"serD|unassigned":14,"vulnD|remoteAccess":1,"vulnD|storage":21}}},
			"traces" : [ 380,366,355,347,339,362,362,344,362,346,344,381,378,340,340,339,371,324,125,128,127,377,126,379,360,352,346,365,365,379,374,371,369,358,352,337,365,373,363,368,360,346]
		},
		{
			"id" : 63,
			"source" :  7,
			"label" : " 12 0",
			"size" : 12,
			"level" : 4,
			"style" : "",
			"isred" :  1,
			"issink" :  0,
			"isblue" :  0,
			"data" :  {"final_counts":{"0":0},"path_counts":{"0":12},"total_final":0,"total_paths":12,"trans_counts":{"1":{"infoD|http(s)":1,"serD|unassigned":9,"vulnD|storage":2}}},
			"traces" : [ 321,207,204,203,202,201,200,196,194,193,181,180]
		},
		{
			"id" : 65,
			"source" :  7,
			"label" : " 10 0",
			"size" : 10,
			"level" : 4,
			"style" : "",
			"isred" :  1,
			"issink" :  0,
			"isblue" :  0,
			"data" :  {"final_counts":{"0":0},"path_counts":{"0":10},"total_final":0,"total_paths":10,"trans_counts":{"1":{"CnC|http(s)":1,"acctManip|http(s)":0,"dManip|http(s)":0,"infoD|http(s)":9,"rPrivEsc|hostingServer":0,"rPrivEsc|http(s)":0,"serD|remoteAccess":0}}},
			"traces" : [ 320,311,310,299,289,286,241,17,322,314]
		},
		{
			"id" : 67,
			"source" :  7,
			"label" : " 5 0",
			"size" : 5,
			"level" : 4,
			"style" : "",
			"isred" :  1,
			"issink" :  0,
			"isblue" :  0,
			"data" :  {"final_counts":{"0":0},"path_counts":{"0":5},"total_final":0,"total_paths":5,"trans_counts":{"1":{"CnC|http(s)":1,"rPrivEsc|http(s)":4}}},
			"traces" : [ 301,318,308,303,302]
		},
		{
			"id" : 87,
			"source" :  15,
			"label" : " 1 4",
			"size" : 5,
			"level" : 3,
			"style" : "",
			"isred" :  1,
			"issink" :  0,
			"isblue" :  0,
			"data" :  {"final_counts":{"0":4},"path_counts":{"0":1},"total_final":4,"total_paths":1,"trans_counts":{"1":{"exfil|unassigned":1}}},
			"traces" : [ 142,97,37,143,237]
		},
		{
			"id" : 91,
			"source" :  16,
			"label" : " 21 4",
			"size" : 25,
			"level" : 4,
			"style" : "",
			"isred" :  1,
			"issink" :  0,
			"isblue" :  0,
			"data" :  {"final_counts":{"0":4},"path_counts":{"0":21},"total_final":4,"total_paths":21,"trans_counts":{"1":{"CnC|http(s)":0,"hostD|http(s)":2,"hostD|surveillance":1,"hostD|wireless":1,"infoD|http(s)":1,"infoD|remoteAccess":0,"rPrivEsc|http(s)":0,"serD|ATCcomm":0,"serD|remoteAccess":4,"serD|unassigned":11,"surf|hostingServer":0,"surf|http(s)":0,"vulnD|remoteAccess":0,"vulnD|storage":0,"vulnD|surveillance":1}}},
			"traces" : [ 396,367,123,121,339,399,136,60,126,128,127,125,242,228,227,225,221,220,130,235,233,232,231,230,229]
		},
		{
			"id" : 99,
			"source" :  18,
			"label" : " 5 0",
			"size" : 5,
			"level" : 2,
			"style" : "",
			"isred" :  1,
			"issink" :  0,
			"isblue" :  0,
			"data" :  {"final_counts":{"0":0},"path_counts":{"0":5},"total_final":0,"total_paths":5,"trans_counts":{"1":{"vulnD|storage":5}}},
			"traces" : [ 256,254,253,252,251]
		},
		{
			"id" : 120,
			"source" :  35,
			"label" : " 39 2",
			"size" : 41,
			"level" : 14,
			"style" : "",
			"isred" :  1,
			"issink" :  0,
			"isblue" :  0,
			"data" :  {"final_counts":{"0":2},"path_counts":{"0":39},"total_final":2,"total_paths":39,"trans_counts":{"1":{"infoD|http(s)":1,"infoD|remoteAccess":13,"serD|remoteAccess":13,"serD|unassigned":9,"surf|remoteAccess":2,"vulnD|storage":1}}},
			"traces" : [ 414,397,283,270,109,108,107,106,102,101,87,86,85,84,54,32,177,176,175,174,169,168,167,166,284,280,279,182,83,82,81,80,79,78,77,76,75,74,73,281,1]
		},
		{
			"id" : 123,
			"source" :  35,
			"label" : " 0 5",
			"size" : 5,
			"level" : 12,
			"style" : "",
			"isred" :  1,
			"issink" :  0,
			"isblue" :  0,
			"data" :  {"final_counts":{"0":5},"total_final":5,"total_paths":0},
			"traces" : [ 277,170,99,41,10]
		},
		{
			"id" : 131,
			"source" :  35,
			"label" : " 0 5",
			"size" : 5,
			"level" : 12,
			"style" : "",
			"isred" :  1,
			"issink" :  0,
			"isblue" :  0,
			"data" :  {"final_counts":{"0":5},"total_final":5,"total_paths":0},
			"traces" : [ 70,222,164,132,171]
		},
		{
			"id" : 178,
			"source" :  63,
			"label" : " 9 0",
			"size" : 9,
			"level" : 5,
			"style" : "",
			"isred" :  1,
			"issink" :  0,
			"isblue" :  0,
			"data" :  {"final_counts":{"0":0},"path_counts":{"0":9},"total_final":0,"total_paths":9,"trans_counts":{"1":{"hostD|http(s)":0,"hostD|remoteAccess":0,"vulnD|http(s)":1,"vulnD|storage":8}}},
			"traces" : [ 321,207,203,202,196,194,193,181,180]
		},
		{
			"id" : 181,
			"source" :  65,
			"label" : " 17 0",
			"size" : 17,
			"level" : 7,
			"style" : "",
			"isred" :  1,
			"issink" :  0,
			"isblue" :  0,
			"data" :  {"final_counts":{"0":0},"path_counts":{"0":17},"total_final":0,"total_paths":17,"trans_counts":{"1":{"rPrivEsc|http(s)":17}}},
			"traces" : [ 320,311,310,299,289,286,241,17,207,203,202,196,194,193,181,180,322]
		},
		{
			"id" : 211,
			"source" :  91,
			"label" : " 21 0",
			"size" : 21,
			"level" : 6,
			"style" : "",
			"isred" :  1,
			"issink" :  0,
			"isblue" :  0,
			"data" :  {"final_counts":{"0":0},"path_counts":{"0":21},"total_final":0,"total_paths":21,"trans_counts":{"1":{"hostD|http(s)":1,"hostD|remoteAccess":1,"vulnD|remoteAccess":1,"vulnD|storage":18}}},
			"traces" : [ 396,235,231,230,229,235,233,232,231,230,229,339,136,228,220,235,233,232,231,230,229]
		},
		{
			"id" : 228,
			"source" :  99,
			"label" : " 0 5",
			"size" : 5,
			"level" : 3,
			"style" : "",
			"isred" :  1,
			"issink" :  0,
			"isblue" :  0,
			"data" :  {"final_counts":{"0":5},"total_final":5,"total_paths":0},
			"traces" : [ 256,254,253,252,251]
		},
		{
			"id" : 247,
			"source" :  120,
			"label" : " 35 1",
			"size" : 36,
			"level" : 17,
			"style" : "",
			"isred" :  1,
			"issink" :  0,
			"isblue" :  0,
			"data" :  {"final_counts":{"0":1},"path_counts":{"0":35},"total_final":1,"total_paths":35,"trans_counts":{"1":{"acctManip|broadcast":13,"hostD|remoteAccess":9,"infoD|remoteAccess":8,"serD|unassigned":4,"vulnD|storage":1}}},
			"traces" : [ 283,270,109,108,107,106,102,101,87,85,84,73,280,279,83,82,80,79,78,77,76,75,74,32,401,71,177,176,175,174,169,168,167,166,284,281]
		},
		{
			"id" : 248,
			"source" :  120,
			"label" : " 12 1",
			"size" : 13,
			"level" : 15,
			"style" : "",
			"isred" :  1,
			"issink" :  0,
			"isblue" :  0,
			"data" :  {"final_counts":{"0":1},"path_counts":{"0":12},"total_final":1,"total_paths":12,"trans_counts":{"1":{"CnC|http(s)":0,"bfCred|unassigned":0,"hostD|http(s)":0,"rPrivEsc|email":0,"serD|unassigned":0,"vulnD|http(s)":0,"vulnD|storage":11,"vulnD|voip":1}}},
			"traces" : [ 414,397,280,279,83,82,80,79,78,77,76,75,74]
		},
		{
			"id" : 306,
			"source" :  178,
			"label" : " 8 0",
			"size" : 8,
			"level" : 6,
			"style" : "",
			"isred" :  1,
			"issink" :  0,
			"isblue" :  0,
			"data" :  {"final_counts":{"0":0},"path_counts":{"0":8},"total_final":0,"total_paths":8,"trans_counts":{"1":{"CnC|http(s)":0,"hostD|http(s)":0,"infoD|http(s)":8,"infoD|remoteAccess":0,"infoD|unassigned":0,"rPrivEsc|http(s)":0,"serD|ATCcomm":0,"serD|remoteAccess":0,"serD|surveillance":0,"serD|unassigned":0,"surf|hostingServer":0,"surf|http(s)":0,"surf|surveillance":0,"vulnD|remoteAccess":0,"vulnD|storage":0}}},
			"traces" : [ 207,203,202,196,194,193,181,180]
		},
		{
			"id" : 310,
			"source" :  181,
			"label" : " 17 0",
			"size" : 17,
			"level" : 8,
			"style" : "",
			"isred" :  1,
			"issink" :  0,
			"isblue" :  0,
			"data" :  {"final_counts":{"0":0},"path_counts":{"0":17},"total_final":0,"total_paths":17,"trans_counts":{"1":{"acctManip|http(s)":17}}},
			"traces" : [ 320,311,310,299,289,286,241,17,207,203,202,196,194,193,181,180,322]
		},
		{
			"id" : 334,
			"source" :  211,
			"label" : " 17 1",
			"size" : 18,
			"level" : 7,
			"style" : "",
			"isred" :  1,
			"issink" :  0,
			"isblue" :  0,
			"data" :  {"final_counts":{"0":1},"path_counts":{"0":17},"total_final":1,"total_paths":17,"trans_counts":{"1":{"CnC|http(s)":0,"hostD|http(s)":0,"infoD|remoteAccess":0,"infoD|unassigned":0,"rPrivEsc|http(s)":0,"serD|remoteAccess":13,"serD|surveillance":0,"serD|unassigned":4,"surf|hostingServer":0,"surf|http(s)":0,"surf|surveillance":0,"vulnD|remoteAccess":0,"vulnD|storage":0}}},
			"traces" : [ 396,235,231,230,229,235,233,232,231,230,229,136,235,233,232,231,230,229]
		},
		{
			"id" : 373,
			"source" :  247,
			"label" : " 6 2",
			"size" : 8,
			"level" : 18,
			"style" : "",
			"isred" :  1,
			"issink" :  0,
			"isblue" :  0,
			"data" :  {"final_counts":{"0":2},"path_counts":{"0":6},"total_final":2,"total_paths":6,"trans_counts":{"1":{"hostD|remoteAccess":6}}},
			"traces" : [ 270,109,108,107,106,102,101,281]
		},
		{
			"id" : 374,
			"source" :  247,
			"label" : " 13 0",
			"size" : 13,
			"level" : 18,
			"style" : "",
			"isred" :  1,
			"issink" :  0,
			"isblue" :  0,
			"data" :  {"final_counts":{"0":0},"path_counts":{"0":13},"total_final":0,"total_paths":13,"trans_counts":{"1":{"netDOS|broadcast":13,"serD|unassigned":0}}},
			"traces" : [ 87,85,84,73,83,82,80,79,78,77,76,75,74]
		},
		{
			"id" : 375,
			"source" :  248,
			"label" : " 11 0",
			"size" : 11,
			"level" : 16,
			"style" : "",
			"isred" :  1,
			"issink" :  0,
			"isblue" :  0,
			"data" :  {"final_counts":{"0":0},"path_counts":{"0":11},"total_final":0,"total_paths":11,"trans_counts":{"1":{"CnC|http(s)":0,"hostD|http(s)":0,"infoD|http(s)":0,"infoD|remoteAccess":11,"rPrivEsc|http(s)":0,"serD|remoteAccess":0,"serD|unassigned":0,"surf|hostingServer":0,"surf|http(s)":0,"vulnD|remoteAccess":0,"vulnD|storage":0,"vulnD|surveillance":0}}},
			"traces" : [ 280,279,83,82,80,79,78,77,76,75,74]
		},
		{
			"id" : 428,
			"source" :  310,
			"label" : " 17 0",
			"size" : 17,
			"level" : 9,
			"style" : "",
			"isred" :  1,
			"issink" :  0,
			"isblue" :  0,
			"data" :  {"final_counts":{"0":0},"path_counts":{"0":17},"total_final":0,"total_paths":17,"trans_counts":{"1":{"remoteexp|http(s)":17}}},
			"traces" : [ 320,311,310,299,289,286,241,17,207,203,202,196,194,193,181,180,322]
		},
		{
			"id" : 449,
			"source" :  334,
			"label" : " 12 1",
			"size" : 13,
			"level" : 8,
			"style" : "",
			"isred" :  1,
			"issink" :  0,
			"isblue" :  0,
			"data" :  {"final_counts":{"0":1},"path_counts":{"0":12},"total_final":1,"total_paths":12,"trans_counts":{"1":{"serD|unassigned":10,"vulnD|storage":2}}},
			"traces" : [ 235,233,232,231,230,229,230,235,233,232,231,230,229]
		},
		{
			"id" : 484,
			"source" :  373,
			"label" : " 0 6",
			"size" : 6,
			"level" : 19,
			"style" : "",
			"isred" :  1,
			"issink" :  0,
			"isblue" :  0,
			"data" :  {"final_counts":{"0":6},"total_final":6,"total_paths":0},
			"traces" : [ 109,108,107,106,102,101]
		},
		{
			"id" : 485,
			"source" :  374,
			"label" : " 0 13",
			"size" : 13,
			"level" : 19,
			"style" : "",
			"isred" :  1,
			"issink" :  0,
			"isblue" :  0,
			"data" :  {"final_counts":{"0":13},"total_final":13,"total_paths":0},
			"traces" : [ 87,85,84,73,83,82,80,79,78,77,76,75,74]
		},
		{
			"id" : 522,
			"source" :  428,
			"label" : " 17 0",
			"size" : 17,
			"level" : 10,
			"style" : "",
			"isred" :  1,
			"issink" :  0,
			"isblue" :  0,
			"data" :  {"final_counts":{"0":0},"path_counts":{"0":17},"total_final":0,"total_paths":17,"trans_counts":{"1":{"ACE|http(s)":2,"CnC|http(s)":15}}},
			"traces" : [ 320,311,310,299,289,286,241,17,207,203,202,196,194,193,181,180,322]
		},
		{
			"id" : 594,
			"source" :  522,
			"label" : " 15 0",
			"size" : 15,
			"level" : 11,
			"style" : "",
			"isred" :  1,
			"issink" :  0,
			"isblue" :  0,
			"data" :  {"final_counts":{"0":0},"path_counts":{"0":15},"total_final":0,"total_paths":15,"trans_counts":{"1":{"ACE|http(s)":15}}},
			"traces" : [ 320,311,310,299,286,241,17,203,202,196,194,193,181,180,322]
		},
		{
			"id" : 660,
			"source" :  594,
			"label" : " 15 0",
			"size" : 15,
			"level" : 12,
			"style" : "",
			"isred" :  1,
			"issink" :  0,
			"isblue" :  0,
			"data" :  {"final_counts":{"0":0},"path_counts":{"0":15},"total_final":0,"total_paths":15,"trans_counts":{"1":{"netDOS|http(s)":2,"resHJ|http(s)":13}}},
			"traces" : [ 320,311,310,299,286,241,17,203,202,196,194,193,181,180,322]
		},
		{
			"id" : 717,
			"source" :  660,
			"label" : " 13 0",
			"size" : 13,
			"level" : 13,
			"style" : "",
			"isred" :  1,
			"issink" :  0,
			"isblue" :  0,
			"data" :  {"final_counts":{"0":0},"path_counts":{"0":13},"total_final":0,"total_paths":13,"trans_counts":{"1":{"dManip|http(s)":13}}},
			"traces" : [ 320,311,310,299,286,17,203,202,196,194,193,181,180]
		},
		{
			"id" : 769,
			"source" :  717,
			"label" : " 13 0",
			"size" : 13,
			"level" : 14,
			"style" : "",
			"isred" :  1,
			"issink" :  0,
			"isblue" :  0,
			"data" :  {"final_counts":{"0":0},"path_counts":{"0":13},"total_final":0,"total_paths":13,"trans_counts":{"1":{"exfil|http(s)":13}}},
			"traces" : [ 320,311,310,299,286,17,203,202,196,194,193,181,180]
		},
		{
			"id" : 815,
			"source" :  769,
			"label" : " 13 0",
			"size" : 13,
			"level" : 15,
			"style" : "",
			"isred" :  1,
			"issink" :  0,
			"isblue" :  0,
			"data" :  {"final_counts":{"0":0},"path_counts":{"0":13},"total_final":0,"total_paths":13,"trans_counts":{"1":{"delivery|http(s)":13}}},
			"traces" : [ 320,311,310,299,286,17,203,202,196,194,193,181,180]
		},
		{
			"id" : 850,
			"source" :  815,
			"label" : " 0 13",
			"size" : 13,
			"level" : 16,
			"style" : "",
			"isred" :  1,
			"issink" :  0,
			"isblue" :  0,
			"data" :  {"final_counts":{"0":13},"total_final":13,"total_paths":0},
			"traces" : [ 320,311,310,299,286,17,203,202,196,194,193,181,180]
		},
		{
			"id" : 2,
			"source" :  0,
			"label" : " 1 0",
			"size" : 1,
			"level" : 1,
			"style" : "",
			"isred" :  0,
			"issink" :  1,
			"isblue" :  1,
			"data" :  {"path_counts":{"0":1},"total_final":0,"total_paths":1,"trans_counts":{"1":{"resHJ|http(s)":1}}},
			"traces" : [ 406]
		},
		{
			"id" : 5,
			"source" :  0,
			"label" : " 4 0",
			"size" : 4,
			"level" : 1,
			"style" : "",
			"isred" :  0,
			"issink" :  1,
			"isblue" :  1,
			"data" :  {"path_counts":{"0":4},"total_final":0,"total_paths":4,"trans_counts":{"1":{"infoD|remoteAccess":3,"serD|unassigned":1}}},
			"traces" : [ 420,243,105,2]
		},
		{
			"id" : 9,
			"source" :  0,
			"label" : " 1 0",
			"size" : 1,
			"level" : 1,
			"style" : "",
			"isred" :  0,
			"issink" :  1,
			"isblue" :  1,
			"data" :  {"path_counts":{"0":1},"total_final":0,"total_paths":1,"trans_counts":{"1":{"exfil|surveillance":1}}},
			"traces" : [ 61]
		},
		{
			"id" : 11,
			"source" :  0,
			"label" : " 2 0",
			"size" : 2,
			"level" : 1,
			"style" : "",
			"isred" :  0,
			"issink" :  1,
			"isblue" :  1,
			"data" :  {"path_counts":{"0":2},"total_final":0,"total_paths":2,"trans_counts":{"1":{"acctManip|hostingServer":1,"vulnD|hostingServer":1}}},
			"traces" : [ 412,209]
		},
		{
			"id" : 13,
			"source" :  0,
			"label" : " 3 0",
			"size" : 3,
			"level" : 1,
			"style" : "",
			"isred" :  0,
			"issink" :  1,
			"isblue" :  1,
			"data" :  {"path_counts":{"0":3},"total_final":0,"total_paths":3,"trans_counts":{"1":{"ACE|http(s)":3}}},
			"traces" : [ 325,292,291]
		},
		{
			"id" : 17,
			"source" :  0,
			"label" : " 2 0",
			"size" : 2,
			"level" : 1,
			"style" : "",
			"isred" :  0,
			"issink" :  1,
			"isblue" :  1,
			"data" :  {"path_counts":{"0":2},"total_final":0,"total_paths":2,"trans_counts":{"1":{"uPrivEsc|hostingServer":2}}},
			"traces" : [ 426,122]
		},
		{
			"id" : 19,
			"source" :  0,
			"label" : " 2 0",
			"size" : 2,
			"level" : 1,
			"style" : "",
			"isred" :  0,
			"issink" :  1,
			"isblue" :  1,
			"data" :  {"path_counts":{"0":2},"total_final":0,"total_paths":2,"trans_counts":{"1":{"surf|wireless":2}}},
			"traces" : [ 206,192]
		},
		{
			"id" : 20,
			"source" :  0,
			"label" : " 1 0",
			"size" : 1,
			"level" : 1,
			"style" : "",
			"isred" :  0,
			"issink" :  1,
			"isblue" :  1,
			"data" :  {"path_counts":{"0":1},"total_final":0,"total_paths":1,"trans_counts":{"1":{"vulnD|storage":1}}},
			"traces" : [ 333]
		},
		{
			"id" : 21,
			"source" :  0,
			"label" : " 1 0",
			"size" : 1,
			"level" : 1,
			"style" : "",
			"isred" :  0,
			"issink" :  1,
			"isblue" :  1,
			"data" :  {"path_counts":{"0":1},"total_final":0,"total_paths":1,"trans_counts":{"1":{"serD|unassigned":1}}},
			"traces" : [ 329]
		},
		{
			"id" : 22,
			"source" :  0,
			"label" : " 2 0",
			"size" : 2,
			"level" : 1,
			"style" : "",
			"isred" :  0,
			"issink" :  1,
			"isblue" :  1,
			"data" :  {"path_counts":{"0":2},"total_final":0,"total_paths":2,"trans_counts":{"1":{"vulnD|storage":2}}},
			"traces" : [ 370,255]
		},
		{
			"id" : 23,
			"source" :  0,
			"label" : " 1 0",
			"size" : 1,
			"level" : 1,
			"style" : "",
			"isred" :  0,
			"issink" :  1,
			"isblue" :  1,
			"data" :  {"path_counts":{"0":1},"total_final":0,"total_paths":1,"trans_counts":{"1":{"CnC|unassigned":1}}},
			"traces" : [ 258]
		},
		{
			"id" : 24,
			"source" :  0,
			"label" : " 1 0",
			"size" : 1,
			"level" : 1,
			"style" : "",
			"isred" :  0,
			"issink" :  1,
			"isblue" :  1,
			"data" :  {"path_counts":{"0":1},"total_final":0,"total_paths":1,"trans_counts":{"1":{"vulnD|storage":1}}},
			"traces" : [ 356]
		},
		{
			"id" : 25,
			"source" :  0,
			"label" : " 4 0",
			"size" : 4,
			"level" : 1,
			"style" : "",
			"isred" :  0,
			"issink" :  1,
			"isblue" :  1,
			"data" :  {"path_counts":{"0":4},"total_final":0,"total_paths":4,"trans_counts":{"1":{"hostD|http(s)":1,"vulnD|remoteAccess":1,"vulnD|storage":2}}},
			"traces" : [ 404,372,361,341]
		},
		{
			"id" : 26,
			"source" :  1,
			"label" : " 4 0",
			"size" : 4,
			"level" : 3,
			"style" : "",
			"isred" :  0,
			"issink" :  1,
			"isblue" :  1,
			"data" :  {"path_counts":{"0":4},"total_final":0,"total_paths":4,"trans_counts":{"1":{"CnC|http(s)":4}}},
			"traces" : [ 269,219,158,0]
		},
		{
			"id" : 27,
			"source" :  1,
			"label" : " 1 0",
			"size" : 1,
			"level" : 3,
			"style" : "",
			"isred" :  0,
			"issink" :  1,
			"isblue" :  1,
			"data" :  {"path_counts":{"0":1},"total_final":0,"total_paths":1,"trans_counts":{"1":{"vulnD|storage":1}}},
			"traces" : [ 146]
		},
		{
			"id" : 29,
			"source" :  1,
			"label" : " 1 0",
			"size" : 1,
			"level" : 3,
			"style" : "",
			"isred" :  0,
			"issink" :  1,
			"isblue" :  1,
			"data" :  {"path_counts":{"0":1},"total_final":0,"total_paths":1,"trans_counts":{"1":{"serD|surveillance":1}}},
			"traces" : [ 390]
		},
		{
			"id" : 30,
			"source" :  1,
			"label" : " 2 0",
			"size" : 2,
			"level" : 3,
			"style" : "",
			"isred" :  0,
			"issink" :  1,
			"isblue" :  1,
			"data" :  {"path_counts":{"0":2},"total_final":0,"total_paths":2,"trans_counts":{"1":{"netDOS|http(s)":2}}},
			"traces" : [ 393,392]
		},
		{
			"id" : 31,
			"source" :  1,
			"label" : " 1 0",
			"size" : 1,
			"level" : 3,
			"style" : "",
			"isred" :  0,
			"issink" :  1,
			"isblue" :  1,
			"data" :  {"path_counts":{"0":1},"total_final":0,"total_paths":1,"trans_counts":{"1":{"netDOS|http(s)":1}}},
			"traces" : [ 120]
		},
		{
			"id" : 32,
			"source" :  1,
			"label" : " 1 0",
			"size" : 1,
			"level" : 3,
			"style" : "",
			"isred" :  0,
			"issink" :  1,
			"isblue" :  1,
			"data" :  {"path_counts":{"0":1},"total_final":0,"total_paths":1,"trans_counts":{"1":{"vulnD|remoteAccess":1}}},
			"traces" : [ 145]
		},
		{
			"id" : 34,
			"source" :  3,
			"label" : " 1 0",
			"size" : 1,
			"level" : 11,
			"style" : "",
			"isred" :  0,
			"issink" :  1,
			"isblue" :  1,
			"data" :  {"path_counts":{"0":1},"total_final":0,"total_paths":1,"trans_counts":{"1":{"serD|unassigned":1}}},
			"traces" : [ 266]
		},
		{
			"id" : 36,
			"source" :  3,
			"label" : " 1 0",
			"size" : 1,
			"level" : 11,
			"style" : "",
			"isred" :  0,
			"issink" :  1,
			"isblue" :  1,
			"data" :  {"path_counts":{"0":1},"total_final":0,"total_paths":1,"trans_counts":{"1":{"hostD|http(s)":1}}},
			"traces" : [ 116]
		},
		{
			"id" : 37,
			"source" :  3,
			"label" : " 4 0",
			"size" : 4,
			"level" : 11,
			"style" : "",
			"isred" :  0,
			"issink" :  1,
			"isblue" :  1,
			"data" :  {"path_counts":{"0":4},"total_final":0,"total_paths":4,"trans_counts":{"1":{"acctManip|broadcast":1,"remoteexp|remoteAccess":1,"vulnD|storage":2}}},
			"traces" : [ 345,323,362,378]
		},
		{
			"id" : 38,
			"source" :  3,
			"label" : " 1 0",
			"size" : 1,
			"level" : 11,
			"style" : "",
			"isred" :  0,
			"issink" :  1,
			"isblue" :  1,
			"data" :  {"path_counts":{"0":1},"total_final":0,"total_paths":1,"trans_counts":{"1":{"vulnD|storage":1}}},
			"traces" : [ 375]
		},
		{
			"id" : 39,
			"source" :  3,
			"label" : " 0 1",
			"size" : 1,
			"level" : 11,
			"style" : "",
			"isred" :  0,
			"issink" :  1,
			"isblue" :  1,
			"data" :  {"final_counts":{"0":1},"total_final":1,"total_paths":0},
			"traces" : [ 262]
		},
		{
			"id" : 40,
			"source" :  3,
			"label" : " 1 0",
			"size" : 1,
			"level" : 11,
			"style" : "",
			"isred" :  0,
			"issink" :  1,
			"isblue" :  1,
			"data" :  {"path_counts":{"0":1},"total_final":0,"total_paths":1,"trans_counts":{"1":{"vulnD|storage":1}}},
			"traces" : [ 337]
		},
		{
			"id" : 41,
			"source" :  3,
			"label" : " 1 0",
			"size" : 1,
			"level" : 11,
			"style" : "",
			"isred" :  0,
			"issink" :  1,
			"isblue" :  1,
			"data" :  {"path_counts":{"0":1},"total_final":0,"total_paths":1,"trans_counts":{"1":{"vulnD|storage":1}}},
			"traces" : [ 386]
		},
		{
			"id" : 43,
			"source" :  4,
			"label" : " 3 0",
			"size" : 3,
			"level" : 4,
			"style" : "",
			"isred" :  0,
			"issink" :  1,
			"isblue" :  1,
			"data" :  {"path_counts":{"0":3},"total_final":0,"total_paths":3,"trans_counts":{"1":{"infoD|remoteAccess":3}}},
			"traces" : [ 90,89,88]
		},
		{
			"id" : 44,
			"source" :  4,
			"label" : " 1 2",
			"size" : 3,
			"level" : 4,
			"style" : "",
			"isred" :  0,
			"issink" :  1,
			"isblue" :  1,
			"data" :  {"final_counts":{"0":2},"path_counts":{"0":1},"total_final":2,"total_paths":1,"trans_counts":{"1":{"bfCred|email":0,"hostD|http(s)":0,"serD|remoteAccess":0,"serD|unassigned":1}}},
			"traces" : [ 263,355,358]
		},
		{
			"id" : 46,
			"source" :  4,
			"label" : " 0 3",
			"size" : 3,
			"level" : 4,
			"style" : "",
			"isred" :  0,
			"issink" :  1,
			"isblue" :  1,
			"data" :  {"final_counts":{"0":3},"total_final":3,"total_paths":0},
			"traces" : [ 350,336,335]
		},
		{
			"id" : 47,
			"source" :  4,
			"label" : " 1 0",
			"size" : 1,
			"level" : 4,
			"style" : "",
			"isred" :  0,
			"issink" :  1,
			"isblue" :  1,
			"data" :  {"path_counts":{"0":1},"total_final":0,"total_paths":1,"trans_counts":{"1":{"serD|unassigned":0,"vulnD|storage":1}}},
			"traces" : [ 354]
		},
		{
			"id" : 48,
			"source" :  4,
			"label" : " 0 4",
			"size" : 4,
			"level" : 4,
			"style" : "",
			"isred" :  0,
			"issink" :  1,
			"isblue" :  1,
			"data" :  {"final_counts":{"0":4},"total_final":4,"total_paths":0},
			"traces" : [ 357,340,374,368]
		},
		{
			"id" : 49,
			"source" :  4,
			"label" : " 1 0",
			"size" : 1,
			"level" : 4,
			"style" : "",
			"isred" :  0,
			"issink" :  1,
			"isblue" :  1,
			"data" :  {"path_counts":{"0":1},"total_final":0,"total_paths":1,"trans_counts":{"1":{"serD|remoteAccess":1}}},
			"traces" : [ 349]
		},
		{
			"id" : 50,
			"source" :  4,
			"label" : " 2 0",
			"size" : 2,
			"level" : 4,
			"style" : "",
			"isred" :  0,
			"issink" :  1,
			"isblue" :  1,
			"data" :  {"path_counts":{"0":2},"total_final":0,"total_paths":2,"trans_counts":{"1":{"vulnD|storage":2}}},
			"traces" : [ 353,344]
		},
		{
			"id" : 51,
			"source" :  4,
			"label" : " 2 0",
			"size" : 2,
			"level" : 4,
			"style" : "",
			"isred" :  0,
			"issink" :  1,
			"isblue" :  1,
			"data" :  {"path_counts":{"0":2},"total_final":0,"total_paths":2,"trans_counts":{"1":{"vulnD|storage":2}}},
			"traces" : [ 364,369]
		},
		{
			"id" : 52,
			"source" :  4,
			"label" : " 1 1",
			"size" : 2,
			"level" : 4,
			"style" : "",
			"isred" :  0,
			"issink" :  1,
			"isblue" :  1,
			"data" :  {"final_counts":{"0":1},"path_counts":{"0":1},"total_final":1,"total_paths":1,"trans_counts":{"1":{"vulnD|storage":1}}},
			"traces" : [ 351,352]
		},
		{
			"id" : 53,
			"source" :  4,
			"label" : " 1 0",
			"size" : 1,
			"level" : 4,
			"style" : "",
			"isred" :  0,
			"issink" :  1,
			"isblue" :  1,
			"data" :  {"path_counts":{"0":1},"total_final":0,"total_paths":1,"trans_counts":{"1":{"acctManip|broadcast":1}}},
			"traces" : [ 348]
		},
		{
			"id" : 54,
			"source" :  4,
			"label" : " 1 0",
			"size" : 1,
			"level" : 4,
			"style" : "",
			"isred" :  0,
			"issink" :  1,
			"isblue" :  1,
			"data" :  {"path_counts":{"0":1},"total_final":0,"total_paths":1,"trans_counts":{"1":{"vulnD|storage":1}}},
			"traces" : [ 376]
		},
		{
			"id" : 57,
			"source" :  6,
			"label" : " 2 0",
			"size" : 2,
			"level" : 3,
			"style" : "",
			"isred" :  0,
			"issink" :  1,
			"isblue" :  1,
			"data" :  {"path_counts":{"0":2},"total_final":0,"total_paths":2,"trans_counts":{"1":{"hostD|remoteAccess":2}}},
			"traces" : [ 179,165]
		},
		{
			"id" : 58,
			"source" :  6,
			"label" : " 2 2",
			"size" : 4,
			"level" : 3,
			"style" : "",
			"isred" :  0,
			"issink" :  1,
			"isblue" :  1,
			"data" :  {"final_counts":{"0":2},"path_counts":{"0":2},"total_final":2,"total_paths":2,"trans_counts":{"1":{"serD|remoteAccess":1,"serD|unassigned":1}}},
			"traces" : [ 100,140,287,91]
		},
		{
			"id" : 59,
			"source" :  6,
			"label" : " 3 0",
			"size" : 3,
			"level" : 3,
			"style" : "",
			"isred" :  0,
			"issink" :  1,
			"isblue" :  1,
			"data" :  {"path_counts":{"0":3},"total_final":0,"total_paths":3,"trans_counts":{"1":{"exfil|http(s)":2,"infoD|http(s)":1}}},
			"traces" : [ 331,330,395]
		},
		{
			"id" : 60,
			"source" :  6,
			"label" : " 1 0",
			"size" : 1,
			"level" : 3,
			"style" : "",
			"isred" :  0,
			"issink" :  1,
			"isblue" :  1,
			"data" :  {"path_counts":{"0":1},"total_final":0,"total_paths":1,"trans_counts":{"1":{"bfCred|unassigned":1}}},
			"traces" : [ 383]
		},
		{
			"id" : 61,
			"source" :  7,
			"label" : " 2 2",
			"size" : 4,
			"level" : 4,
			"style" : "",
			"isred" :  0,
			"issink" :  1,
			"isblue" :  1,
			"data" :  {"final_counts":{"0":2},"path_counts":{"0":2},"total_final":2,"total_paths":2,"trans_counts":{"1":{"rPrivEsc|http(s)":2}}},
			"traces" : [ 313,316,306,304]
		},
		{
			"id" : 62,
			"source" :  7,
			"label" : " 2 0",
			"size" : 2,
			"level" : 4,
			"style" : "",
			"isred" :  0,
			"issink" :  1,
			"isblue" :  1,
			"data" :  {"path_counts":{"0":2},"total_final":0,"total_paths":2,"trans_counts":{"1":{"vulnD|storage":2}}},
			"traces" : [ 267,16]
		},
		{
			"id" : 64,
			"source" :  7,
			"label" : " 2 0",
			"size" : 2,
			"level" : 4,
			"style" : "",
			"isred" :  0,
			"issink" :  1,
			"isblue" :  1,
			"data" :  {"path_counts":{"0":2},"total_final":0,"total_paths":2,"trans_counts":{"1":{"CnC|http(s)":2}}},
			"traces" : [ 317,315]
		},
		{
			"id" : 66,
			"source" :  7,
			"label" : " 1 0",
			"size" : 1,
			"level" : 4,
			"style" : "",
			"isred" :  0,
			"issink" :  1,
			"isblue" :  1,
			"data" :  {"path_counts":{"0":1},"total_final":0,"total_paths":1,"trans_counts":{"1":{"infoD|http(s)":1}}},
			"traces" : [ 18]
		},
		{
			"id" : 68,
			"source" :  7,
			"label" : " 1 0",
			"size" : 1,
			"level" : 4,
			"style" : "",
			"isred" :  0,
			"issink" :  1,
			"isblue" :  1,
			"data" :  {"path_counts":{"0":1},"total_final":0,"total_paths":1,"trans_counts":{"1":{"vulnD|http(s)":1}}},
			"traces" : [ 72]
		},
		{
			"id" : 69,
			"source" :  7,
			"label" : " 1 0",
			"size" : 1,
			"level" : 4,
			"style" : "",
			"isred" :  0,
			"issink" :  1,
			"isblue" :  1,
			"data" :  {"path_counts":{"0":1},"total_final":0,"total_paths":1,"trans_counts":{"1":{"exfil|remoteAccess":1}}},
			"traces" : [ 309]
		},
		{
			"id" : 70,
			"source" :  8,
			"label" : " 1 0",
			"size" : 1,
			"level" : 2,
			"style" : "",
			"isred" :  0,
			"issink" :  1,
			"isblue" :  1,
			"data" :  {"path_counts":{"0":1},"total_final":0,"total_paths":1,"trans_counts":{"1":{"vulnD|storage":1}}},
			"traces" : [ 271]
		},
		{
			"id" : 72,
			"source" :  10,
			"label" : " 1 0",
			"size" : 1,
			"level" : 2,
			"style" : "",
			"isred" :  0,
			"issink" :  1,
			"isblue" :  1,
			"data" :  {"path_counts":{"0":1},"total_final":0,"total_paths":1,"trans_counts":{"1":{"vulnD|hostingServer":1}}},
			"traces" : [ 197]
		},
		{
			"id" : 73,
			"source" :  10,
			"label" : " 1 0",
			"size" : 1,
			"level" : 2,
			"style" : "",
			"isred" :  0,
			"issink" :  1,
			"isblue" :  1,
			"data" :  {"path_counts":{"0":1},"total_final":0,"total_paths":1,"trans_counts":{"1":{"rPrivEsc|hostingServer":1}}},
			"traces" : [ 208]
		},
		{
			"id" : 74,
			"source" :  10,
			"label" : " 1 0",
			"size" : 1,
			"level" : 2,
			"style" : "",
			"isred" :  0,
			"issink" :  1,
			"isblue" :  1,
			"data" :  {"path_counts":{"0":1},"total_final":0,"total_paths":1,"trans_counts":{"1":{"vulnD|storage":1}}},
			"traces" : [ 131]
		},
		{
			"id" : 77,
			"source" :  12,
			"label" : " 1 0",
			"size" : 1,
			"level" : 2,
			"style" : "",
			"isred" :  0,
			"issink" :  1,
			"isblue" :  1,
			"data" :  {"path_counts":{"0":1},"total_final":0,"total_paths":1,"trans_counts":{"1":{"vulnD|unassigned":1}}},
			"traces" : [ 195]
		},
		{
			"id" : 79,
			"source" :  14,
			"label" : " 3 0",
			"size" : 3,
			"level" : 2,
			"style" : "",
			"isred" :  0,
			"issink" :  1,
			"isblue" :  1,
			"data" :  {"path_counts":{"0":3},"total_final":0,"total_paths":3,"trans_counts":{"1":{"acctManip|http(s)":2,"remoteexp|http(s)":1}}},
			"traces" : [ 417,298,47]
		},
		{
			"id" : 80,
			"source" :  14,
			"label" : " 1 0",
			"size" : 1,
			"level" : 2,
			"style" : "",
			"isred" :  0,
			"issink" :  1,
			"isblue" :  1,
			"data" :  {"path_counts":{"0":1},"total_final":0,"total_paths":1,"trans_counts":{"1":{"resHJ|http(s)":1}}},
			"traces" : [ 290]
		},
		{
			"id" : 81,
			"source" :  14,
			"label" : " 1 0",
			"size" : 1,
			"level" : 2,
			"style" : "",
			"isred" :  0,
			"issink" :  1,
			"isblue" :  1,
			"data" :  {"path_counts":{"0":1},"total_final":0,"total_paths":1,"trans_counts":{"1":{"exfil|http(s)":1}}},
			"traces" : [ 422]
		},
		{
			"id" : 82,
			"source" :  14,
			"label" : " 1 0",
			"size" : 1,
			"level" : 2,
			"style" : "",
			"isred" :  0,
			"issink" :  1,
			"isblue" :  1,
			"data" :  {"path_counts":{"0":1},"total_final":0,"total_paths":1,"trans_counts":{"1":{"acctManip|http(s)":1}}},
			"traces" : [ 63]
		},
		{
			"id" : 83,
			"source" :  14,
			"label" : " 1 0",
			"size" : 1,
			"level" : 2,
			"style" : "",
			"isred" :  0,
			"issink" :  1,
			"isblue" :  1,
			"data" :  {"path_counts":{"0":1},"total_final":0,"total_paths":1,"trans_counts":{"1":{"remoteexp|http(s)":1}}},
			"traces" : [ 66]
		},
		{
			"id" : 84,
			"source" :  15,
			"label" : " 1 0",
			"size" : 1,
			"level" : 3,
			"style" : "",
			"isred" :  0,
			"issink" :  1,
			"isblue" :  1,
			"data" :  {"path_counts":{"0":1},"total_final":0,"total_paths":1,"trans_counts":{"1":{"serD|unassigned":1}}},
			"traces" : [ 117]
		},
		{
			"id" : 85,
			"source" :  15,
			"label" : " 4 0",
			"size" : 4,
			"level" : 3,
			"style" : "",
			"isred" :  0,
			"issink" :  1,
			"isblue" :  1,
			"data" :  {"path_counts":{"0":4},"total_final":0,"total_paths":4,"trans_counts":{"1":{"ACE|http(s)":4,"CnC|http(s)":0}}},
			"traces" : [ 312,307,305,300]
		},
		{
			"id" : 86,
			"source" :  15,
			"label" : " 2 1",
			"size" : 3,
			"level" : 3,
			"style" : "",
			"isred" :  0,
			"issink" :  1,
			"isblue" :  1,
			"data" :  {"final_counts":{"0":1},"path_counts":{"0":2},"total_final":1,"total_paths":2,"trans_counts":{"1":{"infoD|unassigned":2}}},
			"traces" : [ 272,238,261]
		},
		{
			"id" : 88,
			"source" :  15,
			"label" : " 1 0",
			"size" : 1,
			"level" : 3,
			"style" : "",
			"isred" :  0,
			"issink" :  1,
			"isblue" :  1,
			"data" :  {"path_counts":{"0":1},"total_final":0,"total_paths":1,"trans_counts":{"1":{"exfil|unassigned":1}}},
			"traces" : [ 257]
		},
		{
			"id" : 89,
			"source" :  15,
			"label" : " 1 0",
			"size" : 1,
			"level" : 3,
			"style" : "",
			"isred" :  0,
			"issink" :  1,
			"isblue" :  1,
			"data" :  {"path_counts":{"0":1},"total_final":0,"total_paths":1,"trans_counts":{"1":{"dDestruct|remoteAccess":1}}},
			"traces" : [ 264]
		},
		{
			"id" : 90,
			"source" :  16,
			"label" : " 0 1",
			"size" : 1,
			"level" : 4,
			"style" : "",
			"isred" :  0,
			"issink" :  1,
			"isblue" :  1,
			"data" :  {"final_counts":{"0":1},"total_final":1,"total_paths":0},
			"traces" : [ 424]
		},
		{
			"id" : 92,
			"source" :  16,
			"label" : " 4 0",
			"size" : 4,
			"level" : 4,
			"style" : "",
			"isred" :  0,
			"issink" :  1,
			"isblue" :  1,
			"data" :  {"path_counts":{"0":4},"total_final":0,"total_paths":4,"trans_counts":{"1":{"serD|remoteAccess":3,"surf|http(s)":1}}},
			"traces" : [ 415,405,387,402]
		},
		{
			"id" : 93,
			"source" :  16,
			"label" : " 2 0",
			"size" : 2,
			"level" : 4,
			"style" : "",
			"isred" :  0,
			"issink" :  1,
			"isblue" :  1,
			"data" :  {"path_counts":{"0":2},"total_final":0,"total_paths":2,"trans_counts":{"1":{"infoD|http(s)":1,"serD|remoteAccess":1}}},
			"traces" : [ 384,59]
		},
		{
			"id" : 94,
			"source" :  16,
			"label" : " 0 2",
			"size" : 2,
			"level" : 4,
			"style" : "",
			"isred" :  0,
			"issink" :  1,
			"isblue" :  1,
			"data" :  {"final_counts":{"0":2},"total_final":2,"total_paths":0},
			"traces" : [ 421,223]
		},
		{
			"id" : 95,
			"source" :  16,
			"label" : " 4 0",
			"size" : 4,
			"level" : 4,
			"style" : "",
			"isred" :  0,
			"issink" :  1,
			"isblue" :  1,
			"data" :  {"path_counts":{"0":4},"total_final":0,"total_paths":4,"trans_counts":{"1":{"hostD|http(s)":1,"infoD|http(s)":1,"rPrivEsc|http(s)":1,"vulnD|http(s)":1}}},
			"traces" : [ 58,56,410,67]
		},
		{
			"id" : 96,
			"source" :  16,
			"label" : " 3 0",
			"size" : 3,
			"level" : 4,
			"style" : "",
			"isred" :  0,
			"issink" :  1,
			"isblue" :  1,
			"data" :  {"path_counts":{"0":3},"total_final":0,"total_paths":3,"trans_counts":{"1":{"remoteexp|hostingServer":1,"remoteexp|http(s)":2}}},
			"traces" : [ 65,62,57]
		},
		{
			"id" : 97,
			"source" :  16,
			"label" : " 0 1",
			"size" : 1,
			"level" : 4,
			"style" : "",
			"isred" :  0,
			"issink" :  1,
			"isblue" :  1,
			"data" :  {"final_counts":{"0":1},"total_final":1,"total_paths":0},
			"traces" : [ 224]
		},
		{
			"id" : 111,
			"source" :  28,
			"label" : " 0 2",
			"size" : 2,
			"level" : 4,
			"style" : "",
			"isred" :  0,
			"issink" :  1,
			"isblue" :  1,
			"data" :  {"final_counts":{"0":2},"total_final":2,"total_paths":0},
			"traces" : [ 245,327]
		},
		{
			"id" : 118,
			"source" :  35,
			"label" : " 2 0",
			"size" : 2,
			"level" : 12,
			"style" : "",
			"isred" :  0,
			"issink" :  1,
			"isblue" :  1,
			"data" :  {"path_counts":{"0":2},"total_final":0,"total_paths":2,"trans_counts":{"1":{"ACE|http(s)":2,"netDOS|http(s)":0}}},
			"traces" : [ 205,191]
		},
		{
			"id" : 119,
			"source" :  35,
			"label" : " 0 1",
			"size" : 1,
			"level" : 12,
			"style" : "",
			"isred" :  0,
			"issink" :  1,
			"isblue" :  1,
			"data" :  {"final_counts":{"0":1},"total_final":1,"total_paths":0},
			"traces" : [ 119]
		},
		{
			"id" : 121,
			"source" :  35,
			"label" : " 4 0",
			"size" : 4,
			"level" : 12,
			"style" : "",
			"isred" :  0,
			"issink" :  1,
			"isblue" :  1,
			"data" :  {"path_counts":{"0":4},"total_final":0,"total_paths":4,"trans_counts":{"1":{"exfil|unassigned":1,"infoD|remoteAccess":1,"infoD|unassigned":1,"surf|surveillance":1}}},
			"traces" : [ 382,199,98,173]
		},
		{
			"id" : 122,
			"source" :  35,
			"label" : " 2 0",
			"size" : 2,
			"level" : 12,
			"style" : "",
			"isred" :  0,
			"issink" :  1,
			"isblue" :  1,
			"data" :  {"path_counts":{"0":2},"total_final":0,"total_paths":2,"trans_counts":{"1":{"infoD|surveillance":1,"vulnD|surveillance":1}}},
			"traces" : [ 22,9]
		},
		{
			"id" : 124,
			"source" :  35,
			"label" : " 3 0",
			"size" : 3,
			"level" : 12,
			"style" : "",
			"isred" :  0,
			"issink" :  1,
			"isblue" :  1,
			"data" :  {"path_counts":{"0":3},"total_final":0,"total_paths":3,"trans_counts":{"1":{"infoD|remoteAccess":1,"serD|remoteAccess":1,"serD|unassigned":1}}},
			"traces" : [ 236,64,178]
		},
		{
			"id" : 125,
			"source" :  35,
			"label" : " 1 0",
			"size" : 1,
			"level" : 12,
			"style" : "",
			"isred" :  0,
			"issink" :  1,
			"isblue" :  1,
			"data" :  {"path_counts":{"0":1},"total_final":0,"total_paths":1,"trans_counts":{"1":{"infoD|hostingServer":1}}},
			"traces" : [ 12]
		},
		{
			"id" : 126,
			"source" :  35,
			"label" : " 2 0",
			"size" : 2,
			"level" : 12,
			"style" : "",
			"isred" :  0,
			"issink" :  1,
			"isblue" :  1,
			"data" :  {"path_counts":{"0":2},"total_final":0,"total_paths":2,"trans_counts":{"1":{"infoD|remoteAccess":1,"serD|unassigned":1}}},
			"traces" : [ 95,172]
		},
		{
			"id" : 127,
			"source" :  35,
			"label" : " 2 0",
			"size" : 2,
			"level" : 12,
			"style" : "",
			"isred" :  0,
			"issink" :  1,
			"isblue" :  1,
			"data" :  {"path_counts":{"0":2},"total_final":0,"total_paths":2,"trans_counts":{"1":{"ACE|http(s)":1,"exfil|http(s)":1}}},
			"traces" : [ 282,278]
		},
		{
			"id" : 128,
			"source" :  35,
			"label" : " 2 0",
			"size" : 2,
			"level" : 12,
			"style" : "",
			"isred" :  0,
			"issink" :  1,
			"isblue" :  1,
			"data" :  {"path_counts":{"0":2},"total_final":0,"total_paths":2,"trans_counts":{"1":{"surf|http(s)":2}}},
			"traces" : [ 216,214]
		},
		{
			"id" : 129,
			"source" :  35,
			"label" : " 3 0",
			"size" : 3,
			"level" : 12,
			"style" : "",
			"isred" :  0,
			"issink" :  1,
			"isblue" :  1,
			"data" :  {"path_counts":{"0":3},"total_final":0,"total_paths":3,"trans_counts":{"1":{"hostD|http(s)":1,"hostD|remoteAccess":1,"vulnD|storage":1}}},
			"traces" : [ 419,40,29]
		},
		{
			"id" : 130,
			"source" :  35,
			"label" : " 0 3",
			"size" : 3,
			"level" : 12,
			"style" : "",
			"isred" :  0,
			"issink" :  1,
			"isblue" :  1,
			"data" :  {"final_counts":{"0":3},"total_final":3,"total_paths":0},
			"traces" : [ 144,161,118]
		},
		{
			"id" : 132,
			"source" :  35,
			"label" : " 0 2",
			"size" : 2,
			"level" : 12,
			"style" : "",
			"isred" :  0,
			"issink" :  1,
			"isblue" :  1,
			"data" :  {"final_counts":{"0":2},"total_final":2,"total_paths":0},
			"traces" : [ 250,381]
		},
		{
			"id" : 133,
			"source" :  35,
			"label" : " 4 0",
			"size" : 4,
			"level" : 12,
			"style" : "",
			"isred" :  0,
			"issink" :  1,
			"isblue" :  1,
			"data" :  {"path_counts":{"0":4},"total_final":0,"total_paths":4,"trans_counts":{"1":{"exfil|unassigned":1,"infoD|unassigned":3}}},
			"traces" : [ 385,226,94,93]
		},
		{
			"id" : 134,
			"source" :  35,
			"label" : " 3 0",
			"size" : 3,
			"level" : 12,
			"style" : "",
			"isred" :  0,
			"issink" :  1,
			"isblue" :  1,
			"data" :  {"path_counts":{"0":3},"total_final":0,"total_paths":3,"trans_counts":{"1":{"infoD|broadcast":2,"vulnD|broadcast":1}}},
			"traces" : [ 129,295,260]
		},
		{
			"id" : 135,
			"source" :  35,
			"label" : " 2 0",
			"size" : 2,
			"level" : 12,
			"style" : "",
			"isred" :  0,
			"issink" :  1,
			"isblue" :  1,
			"data" :  {"path_counts":{"0":2},"total_final":0,"total_paths":2,"trans_counts":{"1":{"vulnD|storage":2}}},
			"traces" : [ 373,347]
		},
		{
			"id" : 136,
			"source" :  35,
			"label" : " 1 0",
			"size" : 1,
			"level" : 12,
			"style" : "",
			"isred" :  0,
			"issink" :  1,
			"isblue" :  1,
			"data" :  {"path_counts":{"0":1},"total_final":0,"total_paths":1,"trans_counts":{"1":{"hostD|remoteAccess":1}}},
			"traces" : [ 157]
		},
		{
			"id" : 137,
			"source" :  35,
			"label" : " 0 1",
			"size" : 1,
			"level" : 12,
			"style" : "",
			"isred" :  0,
			"issink" :  1,
			"isblue" :  1,
			"data" :  {"final_counts":{"0":1},"total_final":1,"total_paths":0},
			"traces" : [ 328]
		},
		{
			"id" : 138,
			"source" :  35,
			"label" : " 0 2",
			"size" : 2,
			"level" : 12,
			"style" : "",
			"isred" :  0,
			"issink" :  1,
			"isblue" :  1,
			"data" :  {"final_counts":{"0":2},"total_final":2,"total_paths":0},
			"traces" : [ 332,240]
		},
		{
			"id" : 139,
			"source" :  35,
			"label" : " 1 0",
			"size" : 1,
			"level" : 12,
			"style" : "",
			"isred" :  0,
			"issink" :  1,
			"isblue" :  1,
			"data" :  {"path_counts":{"0":1},"total_final":0,"total_paths":1,"trans_counts":{"1":{"CnC|unassigned":1}}},
			"traces" : [ 248]
		},
		{
			"id" : 140,
			"source" :  35,
			"label" : " 1 0",
			"size" : 1,
			"level" : 12,
			"style" : "",
			"isred" :  0,
			"issink" :  1,
			"isblue" :  1,
			"data" :  {"path_counts":{"0":1},"total_final":0,"total_paths":1,"trans_counts":{"1":{"vulnD|storage":1}}},
			"traces" : [ 359]
		},
		{
			"id" : 148,
			"source" :  42,
			"label" : " 1 0",
			"size" : 1,
			"level" : 5,
			"style" : "",
			"isred" :  0,
			"issink" :  1,
			"isblue" :  1,
			"data" :  {"path_counts":{"0":1},"total_final":0,"total_paths":1,"trans_counts":{"1":{"vulnD|storage":1}}},
			"traces" : [ 338]
		},
		{
			"id" : 149,
			"source" :  42,
			"label" : " 1 0",
			"size" : 1,
			"level" : 5,
			"style" : "",
			"isred" :  0,
			"issink" :  1,
			"isblue" :  1,
			"data" :  {"path_counts":{"0":1},"total_final":0,"total_paths":1,"trans_counts":{"1":{"infoD|unassigned":1}}},
			"traces" : [ 38]
		},
		{
			"id" : 150,
			"source" :  42,
			"label" : " 0 1",
			"size" : 1,
			"level" : 5,
			"style" : "",
			"isred" :  0,
			"issink" :  1,
			"isblue" :  1,
			"data" :  {"final_counts":{"0":1},"total_final":1,"total_paths":0},
			"traces" : [ 48]
		},
		{
			"id" : 151,
			"source" :  42,
			"label" : " 1 0",
			"size" : 1,
			"level" : 5,
			"style" : "",
			"isred" :  0,
			"issink" :  1,
			"isblue" :  1,
			"data" :  {"path_counts":{"0":1},"total_final":0,"total_paths":1,"trans_counts":{"1":{"vulnD|storage":1}}},
			"traces" : [ 379]
		},
		{
			"id" : 154,
			"source" :  45,
			"label" : " 1 0",
			"size" : 1,
			"level" : 8,
			"style" : "",
			"isred" :  0,
			"issink" :  1,
			"isblue" :  1,
			"data" :  {"path_counts":{"0":1},"total_final":0,"total_paths":1,"trans_counts":{"1":{"serD|unassigned":1}}},
			"traces" : [ 363]
		},
		{
			"id" : 155,
			"source" :  45,
			"label" : " 1 0",
			"size" : 1,
			"level" : 8,
			"style" : "",
			"isred" :  0,
			"issink" :  1,
			"isblue" :  1,
			"data" :  {"path_counts":{"0":1},"total_final":0,"total_paths":1,"trans_counts":{"1":{"vulnD|storage":1}}},
			"traces" : [ 346]
		},
		{
			"id" : 156,
			"source" :  45,
			"label" : " 0 3",
			"size" : 3,
			"level" : 8,
			"style" : "",
			"isred" :  0,
			"issink" :  1,
			"isblue" :  1,
			"data" :  {"final_counts":{"0":3},"total_final":3,"total_paths":0},
			"traces" : [ 360,371,377]
		},
		{
			"id" : 157,
			"source" :  45,
			"label" : " 1 0",
			"size" : 1,
			"level" : 8,
			"style" : "",
			"isred" :  0,
			"issink" :  1,
			"isblue" :  1,
			"data" :  {"path_counts":{"0":1},"total_final":0,"total_paths":1,"trans_counts":{"1":{"acctManip|broadcast":1}}},
			"traces" : [ 365]
		},
		{
			"id" : 177,
			"source" :  63,
			"label" : " 1 0",
			"size" : 1,
			"level" : 5,
			"style" : "",
			"isred" :  0,
			"issink" :  1,
			"isblue" :  1,
			"data" :  {"path_counts":{"0":1},"total_final":0,"total_paths":1,"trans_counts":{"1":{"rPrivEsc|http(s)":1}}},
			"traces" : [ 201]
		},
		{
			"id" : 179,
			"source" :  63,
			"label" : " 2 0",
			"size" : 2,
			"level" : 5,
			"style" : "",
			"isred" :  0,
			"issink" :  1,
			"isblue" :  1,
			"data" :  {"path_counts":{"0":2},"total_final":0,"total_paths":2,"trans_counts":{"1":{"infoD|http(s)":2}}},
			"traces" : [ 204,200]
		},
		{
			"id" : 182,
			"source" :  65,
			"label" : " 1 0",
			"size" : 1,
			"level" : 5,
			"style" : "",
			"isred" :  0,
			"issink" :  1,
			"isblue" :  1,
			"data" :  {"path_counts":{"0":1},"total_final":0,"total_paths":1,"trans_counts":{"1":{"rPrivEsc|http(s)":1}}},
			"traces" : [ 314]
		},
		{
			"id" : 184,
			"source" :  67,
			"label" : " 1 0",
			"size" : 1,
			"level" : 5,
			"style" : "",
			"isred" :  0,
			"issink" :  1,
			"isblue" :  1,
			"data" :  {"path_counts":{"0":1},"total_final":0,"total_paths":1,"trans_counts":{"1":{"rPrivEsc|http(s)":1}}},
			"traces" : [ 303]
		},
		{
			"id" : 185,
			"source" :  67,
			"label" : " 4 0",
			"size" : 4,
			"level" : 5,
			"style" : "",
			"isred" :  0,
			"issink" :  1,
			"isblue" :  1,
			"data" :  {"path_counts":{"0":4},"total_final":0,"total_paths":4,"trans_counts":{"1":{"CnC|http(s)":4}}},
			"traces" : [ 301,318,308,302]
		},
		{
			"id" : 207,
			"source" :  87,
			"label" : " 0 1",
			"size" : 1,
			"level" : 4,
			"style" : "",
			"isred" :  0,
			"issink" :  1,
			"isblue" :  1,
			"data" :  {"final_counts":{"0":1},"total_final":1,"total_paths":0},
			"traces" : [ 142]
		},
		{
			"id" : 210,
			"source" :  91,
			"label" : " 1 0",
			"size" : 1,
			"level" : 5,
			"style" : "",
			"isred" :  0,
			"issink" :  1,
			"isblue" :  1,
			"data" :  {"path_counts":{"0":1},"total_final":0,"total_paths":1,"trans_counts":{"1":{"netDOS|http(s)":1,"rPrivEsc|http(s)":0}}},
			"traces" : [ 242]
		},
		{
			"id" : 212,
			"source" :  91,
			"label" : " 0 2",
			"size" : 2,
			"level" : 5,
			"style" : "",
			"isred" :  0,
			"issink" :  1,
			"isblue" :  1,
			"data" :  {"final_counts":{"0":2},"total_final":2,"total_paths":0},
			"traces" : [ 130,125]
		},
		{
			"id" : 213,
			"source" :  91,
			"label" : " 1 0",
			"size" : 1,
			"level" : 5,
			"style" : "",
			"isred" :  0,
			"issink" :  1,
			"isblue" :  1,
			"data" :  {"path_counts":{"0":1},"total_final":0,"total_paths":1,"trans_counts":{"1":{"infoD|unassigned":1}}},
			"traces" : [ 123]
		},
		{
			"id" : 214,
			"source" :  91,
			"label" : " 1 0",
			"size" : 1,
			"level" : 5,
			"style" : "",
			"isred" :  0,
			"issink" :  1,
			"isblue" :  1,
			"data" :  {"path_counts":{"0":1},"total_final":0,"total_paths":1,"trans_counts":{"1":{"uPrivEsc|surveillance":1}}},
			"traces" : [ 60]
		},
		{
			"id" : 215,
			"source" :  91,
			"label" : " 4 0",
			"size" : 4,
			"level" : 5,
			"style" : "",
			"isred" :  0,
			"issink" :  1,
			"isblue" :  1,
			"data" :  {"path_counts":{"0":4},"total_final":0,"total_paths":4,"trans_counts":{"1":{"bfCred|unassigned":1,"hostD|hostingServer":1,"hostD|unassigned":1,"serD|unassigned":0,"vulnD|storage":1}}},
			"traces" : [ 367,227,225,221]
		},
		{
			"id" : 216,
			"source" :  91,
			"label" : " 1 0",
			"size" : 1,
			"level" : 5,
			"style" : "",
			"isred" :  0,
			"issink" :  1,
			"isblue" :  1,
			"data" :  {"path_counts":{"0":1},"total_final":0,"total_paths":1,"trans_counts":{"1":{"infoD|unassigned":1}}},
			"traces" : [ 121]
		},
		{
			"id" : 244,
			"source" :  120,
			"label" : " 1 0",
			"size" : 1,
			"level" : 15,
			"style" : "",
			"isred" :  0,
			"issink" :  1,
			"isblue" :  1,
			"data" :  {"path_counts":{"0":1},"total_final":0,"total_paths":1,"trans_counts":{"1":{"bfCred|unassigned":1}}},
			"traces" : [ 86]
		},
		{
			"id" : 245,
			"source" :  120,
			"label" : " 1 0",
			"size" : 1,
			"level" : 15,
			"style" : "",
			"isred" :  0,
			"issink" :  1,
			"isblue" :  1,
			"data" :  {"path_counts":{"0":1},"total_final":0,"total_paths":1,"trans_counts":{"1":{"infoD|remoteAccess":1}}},
			"traces" : [ 81]
		},
		{
			"id" : 246,
			"source" :  120,
			"label" : " 2 0",
			"size" : 2,
			"level" : 15,
			"style" : "",
			"isred" :  0,
			"issink" :  1,
			"isblue" :  1,
			"data" :  {"path_counts":{"0":2},"total_final":0,"total_paths":2,"trans_counts":{"1":{"infoD|remoteAccess":1,"vulnD|remoteAccess":1}}},
			"traces" : [ 1,182]
		},
		{
			"id" : 307,
			"source" :  178,
			"label" : " 1 0",
			"size" : 1,
			"level" : 6,
			"style" : "",
			"isred" :  0,
			"issink" :  1,
			"isblue" :  1,
			"data" :  {"path_counts":{"0":1},"total_final":0,"total_paths":1,"trans_counts":{"1":{"infoD|http(s)":1}}},
			"traces" : [ 321]
		},
		{
			"id" : 335,
			"source" :  211,
			"label" : " 1 0",
			"size" : 1,
			"level" : 7,
			"style" : "",
			"isred" :  0,
			"issink" :  1,
			"isblue" :  1,
			"data" :  {"path_counts":{"0":1},"total_final":0,"total_paths":1,"trans_counts":{"1":{"serD|unassigned":1}}},
			"traces" : [ 228]
		},
		{
			"id" : 336,
			"source" :  211,
			"label" : " 1 0",
			"size" : 1,
			"level" : 7,
			"style" : "",
			"isred" :  0,
			"issink" :  1,
			"isblue" :  1,
			"data" :  {"path_counts":{"0":1},"total_final":0,"total_paths":1,"trans_counts":{"1":{"serD|unassigned":1}}},
			"traces" : [ 220]
		},
		{
			"id" : 337,
			"source" :  211,
			"label" : " 1 0",
			"size" : 1,
			"level" : 7,
			"style" : "",
			"isred" :  0,
			"issink" :  1,
			"isblue" :  1,
			"data" :  {"path_counts":{"0":1},"total_final":0,"total_paths":1,"trans_counts":{"1":{"serD|unassigned":1}}},
			"traces" : [ 339]
		},
		{
			"id" : 371,
			"source" :  247,
			"label" : " 4 0",
			"size" : 4,
			"level" : 18,
			"style" : "",
			"isred" :  0,
			"issink" :  1,
			"isblue" :  1,
			"data" :  {"path_counts":{"0":4},"total_final":0,"total_paths":4,"trans_counts":{"1":{"vulnD|storage":4}}},
			"traces" : [ 284,280,279,401]
		},
		{
			"id" : 372,
			"source" :  247,
			"label" : " 1 0",
			"size" : 1,
			"level" : 18,
			"style" : "",
			"isred" :  0,
			"issink" :  1,
			"isblue" :  1,
			"data" :  {"path_counts":{"0":1},"total_final":0,"total_paths":1,"trans_counts":{"1":{"infoD|remoteAccess":1}}},
			"traces" : [ 71]
		},
		{
			"id" : 376,
			"source" :  248,
			"label" : " 0 1",
			"size" : 1,
			"level" : 16,
			"style" : "",
			"isred" :  0,
			"issink" :  1,
			"isblue" :  1,
			"data" :  {"final_counts":{"0":1},"total_final":1,"total_paths":0},
			"traces" : [ 397]
		},
		{
			"id" : 448,
			"source" :  334,
			"label" : " 4 0",
			"size" : 4,
			"level" : 8,
			"style" : "",
			"isred" :  0,
			"issink" :  1,
			"isblue" :  1,
			"data" :  {"path_counts":{"0":4},"total_final":0,"total_paths":4,"trans_counts":{"1":{"vulnD|storage":4}}},
			"traces" : [ 136,235,231,229]
		},
		{
			"id" : 533,
			"source" :  449,
			"label" : " 2 0",
			"size" : 2,
			"level" : 9,
			"style" : "",
			"isred" :  0,
			"issink" :  1,
			"isblue" :  1,
			"data" :  {"path_counts":{"0":2},"total_final":0,"total_paths":2,"trans_counts":{"1":{"serD|unassigned":2}}},
			"traces" : [ 230,232]
		},
		{
			"id" : 595,
			"source" :  522,
			"label" : " 2 0",
			"size" : 2,
			"level" : 11,
			"style" : "",
			"isred" :  0,
			"issink" :  1,
			"isblue" :  1,
			"data" :  {"path_counts":{"0":2},"total_final":0,"total_paths":2,"trans_counts":{"1":{"dManip|http(s)":1,"resHJ|http(s)":1}}},
			"traces" : [ 289,207]
		},
		{
			"id" : 716,
			"source" :  660,
			"label" : " 2 0",
			"size" : 2,
			"level" : 13,
			"style" : "",
			"isred" :  0,
			"issink" :  1,
			"isblue" :  1,
			"data" :  {"path_counts":{"0":2},"total_final":0,"total_paths":2,"trans_counts":{"1":{"resHJ|http(s)":2}}},
			"traces" : [ 241,322]
		}
	],
	"edges" : [
		{
			"id" : "0_1",
			"source" : "0",
			"target" : "1",
			"name": "infoD|http(s)",
			"appearances": "20 "}
,
		{
			"id" : "0_2",
			"source" : "0",
			"target" : "2",
			"name": "CnC|http(s)",
			"appearances": "1 "}
,
		{
			"id" : "0_3",
			"source" : "0",
			"target" : "3",
			"name": "serD|unassigned",
			"appearances": "181 "}
,
		{
			"id" : "0_4",
			"source" : "0",
			"target" : "4",
			"name": "vulnD|storage",
			"appearances": "35 "}
,
		{
			"id" : "0_120",
			"source" : "0",
			"target" : "120",
			"name": "hostD|remoteAccess",
			"appearances": "15 "}
,
		{
			"id" : "0_5",
			"source" : "0",
			"target" : "5",
			"name": "surf|remoteAccess",
			"appearances": "4 "}
,
		{
			"id" : "0_6",
			"source" : "0",
			"target" : "6",
			"name": "hostD|http(s)",
			"appearances": "41 "}
,
		{
			"id" : "0_7",
			"source" : "0",
			"target" : "7",
			"name": "surf|http(s)",
			"appearances": "30 "}
,
		{
			"id" : "0_8",
			"source" : "0",
			"target" : "8",
			"name": "hostD|surveillance",
			"appearances": "6 "}
,
		{
			"id" : "0_9",
			"source" : "0",
			"target" : "9",
			"name": "infoD|surveillance",
			"appearances": "1 "}
,
		{
			"id" : "0_10",
			"source" : "0",
			"target" : "10",
			"name": "hostD|hostingServer",
			"appearances": "10 "}
,
		{
			"id" : "0_11",
			"source" : "0",
			"target" : "11",
			"name": "surf|hostingServer",
			"appearances": "2 "}
,
		{
			"id" : "0_12",
			"source" : "0",
			"target" : "12",
			"name": "hostD|unassigned",
			"appearances": "6 "}
,
		{
			"id" : "0_13",
			"source" : "0",
			"target" : "13",
			"name": "rPrivEsc|http(s)",
			"appearances": "3 "}
,
		{
			"id" : "0_14",
			"source" : "0",
			"target" : "14",
			"name": "vulnD|http(s)",
			"appearances": "7 "}
,
		{
			"id" : "0_45",
			"source" : "0",
			"target" : "45",
			"name": "vulnD|remoteAccess",
			"appearances": "7 "}
,
		{
			"id" : "0_15",
			"source" : "0",
			"target" : "15",
			"name": "infoD|unassigned",
			"appearances": "10 "}
,
		{
			"id" : "0_16",
			"source" : "0",
			"target" : "16",
			"name": "serD|remoteAccess",
			"appearances": "29 "}
,
		{
			"id" : "0_17",
			"source" : "0",
			"target" : "17",
			"name": "uPrivEsc|hostingServer",
			"appearances": "2 "}
,
		{
			"id" : "0_18",
			"source" : "0",
			"target" : "18",
			"name": "acctManip|broadcast",
			"appearances": "5 "}
,
		{
			"id" : "0_19",
			"source" : "0",
			"target" : "19",
			"name": "hostD|wireless",
			"appearances": "2 "}
,
		{
			"id" : "0_20",
			"source" : "0",
			"target" : "20",
			"name": "serD|surveillance",
			"appearances": "1 "}
,
		{
			"id" : "0_21",
			"source" : "0",
			"target" : "21",
			"name": "exfil|remoteAccess",
			"appearances": "1 "}
,
		{
			"id" : "0_22",
			"source" : "0",
			"target" : "22",
			"name": "serD|ATCcomm",
			"appearances": "2 "}
,
		{
			"id" : "0_23",
			"source" : "0",
			"target" : "23",
			"name": "CnC|unassigned",
			"appearances": "1 "}
,
		{
			"id" : "0_24",
			"source" : "0",
			"target" : "24",
			"name": "serD|storage",
			"appearances": "1 "}
,
		{
			"id" : "0_25",
			"source" : "0",
			"target" : "25",
			"name": "infoD|nameserver",
			"appearances": "4 "}
,
		{
			"id" : "1_26",
			"source" : "1",
			"target" : "26",
			"name": "infoD|http(s)",
			"appearances": "4 "}
,
		{
			"id" : "1_27",
			"source" : "1",
			"target" : "27",
			"name": "serD|unassigned",
			"appearances": "1 "}
,
		{
			"id" : "1_7",
			"source" : "1",
			"target" : "7",
			"name": "surf|http(s)",
			"appearances": "11 "}
,
		{
			"id" : "1_28",
			"source" : "1",
			"target" : "28",
			"name": "netDOS|http(s)",
			"appearances": "15 "}
,
		{
			"id" : "1_29",
			"source" : "1",
			"target" : "29",
			"name": "hostD|hostingServer",
			"appearances": "1 "}
,
		{
			"id" : "1_30",
			"source" : "1",
			"target" : "30",
			"name": "remoteexp|http(s)",
			"appearances": "2 "}
,
		{
			"id" : "1_31",
			"source" : "1",
			"target" : "31",
			"name": "uPrivEsc|hostingServer",
			"appearances": "1 "}
,
		{
			"id" : "1_32",
			"source" : "1",
			"target" : "32",
			"name": "serD|surveillance",
			"appearances": "1 "}
,
		{
			"id" : "3_34",
			"source" : "3",
			"target" : "34",
			"name": "CnC|http(s)",
			"appearances": "1 "}
,
		{
			"id" : "3_3",
			"source" : "3",
			"target" : "3",
			"name": "serD|unassigned",
			"appearances": "7 "}
,
		{
			"id" : "3_35",
			"source" : "3",
			"target" : "35",
			"name": "vulnD|storage",
			"appearances": "446 "}
,
		{
			"id" : "3_36",
			"source" : "3",
			"target" : "36",
			"name": "vulnD|http(s)",
			"appearances": "1 "}
,
		{
			"id" : "3_37",
			"source" : "3",
			"target" : "37",
			"name": "vulnD|remoteAccess",
			"appearances": "4 "}
,
		{
			"id" : "3_38",
			"source" : "3",
			"target" : "38",
			"name": "infoD|unassigned",
			"appearances": "1 "}
,
		{
			"id" : "3_39",
			"source" : "3",
			"target" : "39",
			"name": "bfCred|email",
			"appearances": "1 "}
,
		{
			"id" : "3_40",
			"source" : "3",
			"target" : "40",
			"name": "serD|storage",
			"appearances": "1 "}
,
		{
			"id" : "3_41",
			"source" : "3",
			"target" : "41",
			"name": "serD|broadcast",
			"appearances": "1 "}
,
		{
			"id" : "4_42",
			"source" : "4",
			"target" : "42",
			"name": "serD|unassigned",
			"appearances": "39 "}
,
		{
			"id" : "4_4",
			"source" : "4",
			"target" : "4",
			"name": "vulnD|storage",
			"appearances": "92 "}
,
		{
			"id" : "4_43",
			"source" : "4",
			"target" : "43",
			"name": "hostD|remoteAccess",
			"appearances": "3 "}
,
		{
			"id" : "4_44",
			"source" : "4",
			"target" : "44",
			"name": "hostD|http(s)",
			"appearances": "3 "}
,
		{
			"id" : "4_45",
			"source" : "4",
			"target" : "45",
			"name": "vulnD|remoteAccess",
			"appearances": "20 "}
,
		{
			"id" : "4_46",
			"source" : "4",
			"target" : "46",
			"name": "exfil|unassigned",
			"appearances": "3 "}
,
		{
			"id" : "4_47",
			"source" : "4",
			"target" : "47",
			"name": "serD|remoteAccess",
			"appearances": "1 "}
,
		{
			"id" : "4_48",
			"source" : "4",
			"target" : "48",
			"name": "acctManip|broadcast",
			"appearances": "4 "}
,
		{
			"id" : "4_49",
			"source" : "4",
			"target" : "49",
			"name": "hostD|wireless",
			"appearances": "1 "}
,
		{
			"id" : "4_50",
			"source" : "4",
			"target" : "50",
			"name": "serD|surveillance",
			"appearances": "2 "}
,
		{
			"id" : "4_51",
			"source" : "4",
			"target" : "51",
			"name": "serD|ATCcomm",
			"appearances": "2 "}
,
		{
			"id" : "4_52",
			"source" : "4",
			"target" : "52",
			"name": "serD|storage",
			"appearances": "2 "}
,
		{
			"id" : "4_53",
			"source" : "4",
			"target" : "53",
			"name": "infoD|nameserver",
			"appearances": "1 "}
,
		{
			"id" : "4_54",
			"source" : "4",
			"target" : "54",
			"name": "serD|broadcast",
			"appearances": "1 "}
,
		{
			"id" : "6_3",
			"source" : "6",
			"target" : "3",
			"name": "serD|unassigned",
			"appearances": "36 "}
,
		{
			"id" : "6_57",
			"source" : "6",
			"target" : "57",
			"name": "infoD|remoteAccess",
			"appearances": "2 "}
,
		{
			"id" : "6_58",
			"source" : "6",
			"target" : "58",
			"name": "hostD|http(s)",
			"appearances": "4 "}
,
		{
			"id" : "6_59",
			"source" : "6",
			"target" : "59",
			"name": "vulnD|http(s)",
			"appearances": "3 "}
,
		{
			"id" : "6_16",
			"source" : "6",
			"target" : "16",
			"name": "serD|remoteAccess",
			"appearances": "13 "}
,
		{
			"id" : "6_60",
			"source" : "6",
			"target" : "60",
			"name": "bfCred|email",
			"appearances": "1 "}
,
		{
			"id" : "7_1",
			"source" : "7",
			"target" : "1",
			"name": "infoD|http(s)",
			"appearances": "16 "}
,
		{
			"id" : "7_61",
			"source" : "7",
			"target" : "61",
			"name": "CnC|http(s)",
			"appearances": "4 "}
,
		{
			"id" : "7_62",
			"source" : "7",
			"target" : "62",
			"name": "serD|unassigned",
			"appearances": "2 "}
,
		{
			"id" : "7_63",
			"source" : "7",
			"target" : "63",
			"name": "hostD|http(s)",
			"appearances": "12 "}
,
		{
			"id" : "7_64",
			"source" : "7",
			"target" : "64",
			"name": "rPrivEsc|http(s)",
			"appearances": "2 "}
,
		{
			"id" : "7_65",
			"source" : "7",
			"target" : "65",
			"name": "vulnD|http(s)",
			"appearances": "10 "}
,
		{
			"id" : "7_66",
			"source" : "7",
			"target" : "66",
			"name": "vulnD|wireless",
			"appearances": "1 "}
,
		{
			"id" : "7_67",
			"source" : "7",
			"target" : "67",
			"name": "infoD|unassigned",
			"appearances": "5 "}
,
		{
			"id" : "7_68",
			"source" : "7",
			"target" : "68",
			"name": "serD|remoteAccess",
			"appearances": "1 "}
,
		{
			"id" : "7_69",
			"source" : "7",
			"target" : "69",
			"name": "rPrivEsc|remoteAccess",
			"appearances": "1 "}
,
		{
			"id" : "8_3",
			"source" : "8",
			"target" : "3",
			"name": "serD|unassigned",
			"appearances": "5 "}
,
		{
			"id" : "8_70",
			"source" : "8",
			"target" : "70",
			"name": "serD|surveillance",
			"appearances": "1 "}
,
		{
			"id" : "10_3",
			"source" : "10",
			"target" : "3",
			"name": "serD|unassigned",
			"appearances": "7 "}
,
		{
			"id" : "10_72",
			"source" : "10",
			"target" : "72",
			"name": "surf|hostingServer",
			"appearances": "1 "}
,
		{
			"id" : "10_73",
			"source" : "10",
			"target" : "73",
			"name": "infoD|hostingServer",
			"appearances": "1 "}
,
		{
			"id" : "10_74",
			"source" : "10",
			"target" : "74",
			"name": "serD|remoteAccess",
			"appearances": "1 "}
,
		{
			"id" : "12_3",
			"source" : "12",
			"target" : "3",
			"name": "serD|unassigned",
			"appearances": "5 "}
,
		{
			"id" : "12_77",
			"source" : "12",
			"target" : "77",
			"name": "surf|unassigned",
			"appearances": "1 "}
,
		{
			"id" : "14_79",
			"source" : "14",
			"target" : "79",
			"name": "rPrivEsc|http(s)",
			"appearances": "3 "}
,
		{
			"id" : "14_80",
			"source" : "14",
			"target" : "80",
			"name": "acctManip|http(s)",
			"appearances": "1 "}
,
		{
			"id" : "14_81",
			"source" : "14",
			"target" : "81",
			"name": "dManip|http(s)",
			"appearances": "1 "}
,
		{
			"id" : "14_82",
			"source" : "14",
			"target" : "82",
			"name": "serD|remoteAccess",
			"appearances": "1 "}
,
		{
			"id" : "14_83",
			"source" : "14",
			"target" : "83",
			"name": "rPrivEsc|hostingServer",
			"appearances": "1 "}
,
		{
			"id" : "15_3",
			"source" : "15",
			"target" : "3",
			"name": "serD|unassigned",
			"appearances": "5 "}
,
		{
			"id" : "15_84",
			"source" : "15",
			"target" : "84",
			"name": "hostD|http(s)",
			"appearances": "1 "}
,
		{
			"id" : "15_85",
			"source" : "15",
			"target" : "85",
			"name": "rPrivEsc|http(s)",
			"appearances": "4 "}
,
		{
			"id" : "15_86",
			"source" : "15",
			"target" : "86",
			"name": "infoD|unassigned",
			"appearances": "3 "}
,
		{
			"id" : "15_87",
			"source" : "15",
			"target" : "87",
			"name": "exfil|unassigned",
			"appearances": "5 "}
,
		{
			"id" : "15_88",
			"source" : "15",
			"target" : "88",
			"name": "uPrivEsc|hostingServer",
			"appearances": "1 "}
,
		{
			"id" : "15_89",
			"source" : "15",
			"target" : "89",
			"name": "dDestruct|remoteAccess",
			"appearances": "1 "}
,
		{
			"id" : "16_90",
			"source" : "16",
			"target" : "90",
			"name": "CnC|http(s)",
			"appearances": "1 "}
,
		{
			"id" : "16_3",
			"source" : "16",
			"target" : "3",
			"name": "serD|unassigned",
			"appearances": "6 "}
,
		{
			"id" : "16_91",
			"source" : "16",
			"target" : "91",
			"name": "vulnD|storage",
			"appearances": "25 "}
,
		{
			"id" : "16_92",
			"source" : "16",
			"target" : "92",
			"name": "hostD|http(s)",
			"appearances": "4 "}
,
		{
			"id" : "16_93",
			"source" : "16",
			"target" : "93",
			"name": "surf|http(s)",
			"appearances": "2 "}
,
		{
			"id" : "16_94",
			"source" : "16",
			"target" : "94",
			"name": "bfCred|unassigned",
			"appearances": "2 "}
,
		{
			"id" : "16_95",
			"source" : "16",
			"target" : "95",
			"name": "vulnD|http(s)",
			"appearances": "4 "}
,
		{
			"id" : "16_16",
			"source" : "16",
			"target" : "16",
			"name": "serD|remoteAccess",
			"appearances": "20 "}
,
		{
			"id" : "16_96",
			"source" : "16",
			"target" : "96",
			"name": "PAexp|http(s)",
			"appearances": "3 "}
,
		{
			"id" : "16_97",
			"source" : "16",
			"target" : "97",
			"name": "rPrivEsc|email",
			"appearances": "1 "}
,
		{
			"id" : "18_99",
			"source" : "18",
			"target" : "99",
			"name": "serD|unassigned",
			"appearances": "5 "}
,
		{
			"id" : "28_111",
			"source" : "28",
			"target" : "111",
			"name": "resHJ|http(s)",
			"appearances": "2 "}
,
		{
			"id" : "35_118",
			"source" : "35",
			"target" : "118",
			"name": "infoD|http(s)",
			"appearances": "2 "}
,
		{
			"id" : "35_119",
			"source" : "35",
			"target" : "119",
			"name": "CnC|http(s)",
			"appearances": "1 "}
,
		{
			"id" : "35_3",
			"source" : "35",
			"target" : "3",
			"name": "serD|unassigned",
			"appearances": "189 "}
,
		{
			"id" : "35_35",
			"source" : "35",
			"target" : "35",
			"name": "vulnD|storage",
			"appearances": "44 "}
,
		{
			"id" : "35_120",
			"source" : "35",
			"target" : "120",
			"name": "hostD|remoteAccess",
			"appearances": "17 "}
,
		{
			"id" : "35_247",
			"source" : "35",
			"target" : "247",
			"name": "infoD|remoteAccess",
			"appearances": "12 "}
,
		{
			"id" : "35_6",
			"source" : "35",
			"target" : "6",
			"name": "hostD|http(s)",
			"appearances": "24 "}
,
		{
			"id" : "35_7",
			"source" : "35",
			"target" : "7",
			"name": "surf|http(s)",
			"appearances": "14 "}
,
		{
			"id" : "35_121",
			"source" : "35",
			"target" : "121",
			"name": "hostD|surveillance",
			"appearances": "4 "}
,
		{
			"id" : "35_122",
			"source" : "35",
			"target" : "122",
			"name": "surf|surveillance",
			"appearances": "2 "}
,
		{
			"id" : "35_123",
			"source" : "35",
			"target" : "123",
			"name": "bfCred|unassigned",
			"appearances": "5 "}
,
		{
			"id" : "35_124",
			"source" : "35",
			"target" : "124",
			"name": "hostD|hostingServer",
			"appearances": "3 "}
,
		{
			"id" : "35_125",
			"source" : "35",
			"target" : "125",
			"name": "surf|hostingServer",
			"appearances": "1 "}
,
		{
			"id" : "35_126",
			"source" : "35",
			"target" : "126",
			"name": "hostD|unassigned",
			"appearances": "2 "}
,
		{
			"id" : "35_127",
			"source" : "35",
			"target" : "127",
			"name": "rPrivEsc|http(s)",
			"appearances": "2 "}
,
		{
			"id" : "35_128",
			"source" : "35",
			"target" : "128",
			"name": "vulnD|http(s)",
			"appearances": "2 "}
,
		{
			"id" : "35_129",
			"source" : "35",
			"target" : "129",
			"name": "serD|voip",
			"appearances": "3 "}
,
		{
			"id" : "35_45",
			"source" : "35",
			"target" : "45",
			"name": "vulnD|remoteAccess",
			"appearances": "10 "}
,
		{
			"id" : "35_15",
			"source" : "35",
			"target" : "15",
			"name": "infoD|unassigned",
			"appearances": "12 "}
,
		{
			"id" : "35_16",
			"source" : "35",
			"target" : "16",
			"name": "serD|remoteAccess",
			"appearances": "12 "}
,
		{
			"id" : "35_130",
			"source" : "35",
			"target" : "130",
			"name": "uPrivEsc|hostingServer",
			"appearances": "3 "}
,
		{
			"id" : "35_131",
			"source" : "35",
			"target" : "131",
			"name": "bfCred|email",
			"appearances": "5 "}
,
		{
			"id" : "35_132",
			"source" : "35",
			"target" : "132",
			"name": "acctManip|broadcast",
			"appearances": "2 "}
,
		{
			"id" : "35_133",
			"source" : "35",
			"target" : "133",
			"name": "hostD|wireless",
			"appearances": "4 "}
,
		{
			"id" : "35_134",
			"source" : "35",
			"target" : "134",
			"name": "surf|broadcast",
			"appearances": "3 "}
,
		{
			"id" : "35_135",
			"source" : "35",
			"target" : "135",
			"name": "serD|surveillance",
			"appearances": "2 "}
,
		{
			"id" : "35_136",
			"source" : "35",
			"target" : "136",
			"name": "vulnD|voip",
			"appearances": "1 "}
,
		{
			"id" : "35_137",
			"source" : "35",
			"target" : "137",
			"name": "exfil|remoteAccess",
			"appearances": "1 "}
,
		{
			"id" : "35_138",
			"source" : "35",
			"target" : "138",
			"name": "exfil|broadcast",
			"appearances": "2 "}
,
		{
			"id" : "35_139",
			"source" : "35",
			"target" : "139",
			"name": "CnC|surveillance",
			"appearances": "1 "}
,
		{
			"id" : "35_140",
			"source" : "35",
			"target" : "140",
			"name": "serD|broadcast",
			"appearances": "1 "}
,
		{
			"id" : "42_148",
			"source" : "42",
			"target" : "148",
			"name": "serD|unassigned",
			"appearances": "1 "}
,
		{
			"id" : "42_4",
			"source" : "42",
			"target" : "4",
			"name": "vulnD|storage",
			"appearances": "30 "}
,
		{
			"id" : "42_149",
			"source" : "42",
			"target" : "149",
			"name": "hostD|surveillance",
			"appearances": "1 "}
,
		{
			"id" : "42_150",
			"source" : "42",
			"target" : "150",
			"name": "hostD|hostingServer",
			"appearances": "1 "}
,
		{
			"id" : "42_45",
			"source" : "42",
			"target" : "45",
			"name": "vulnD|remoteAccess",
			"appearances": "5 "}
,
		{
			"id" : "42_151",
			"source" : "42",
			"target" : "151",
			"name": "serD|surveillance",
			"appearances": "1 "}
,
		{
			"id" : "45_3",
			"source" : "45",
			"target" : "3",
			"name": "serD|unassigned",
			"appearances": "14 "}
,
		{
			"id" : "45_4",
			"source" : "45",
			"target" : "4",
			"name": "vulnD|storage",
			"appearances": "21 "}
,
		{
			"id" : "45_154",
			"source" : "45",
			"target" : "154",
			"name": "vulnD|remoteAccess",
			"appearances": "1 "}
,
		{
			"id" : "45_155",
			"source" : "45",
			"target" : "155",
			"name": "serD|remoteAccess",
			"appearances": "1 "}
,
		{
			"id" : "45_156",
			"source" : "45",
			"target" : "156",
			"name": "acctManip|broadcast",
			"appearances": "3 "}
,
		{
			"id" : "45_157",
			"source" : "45",
			"target" : "157",
			"name": "infoD|nameserver",
			"appearances": "1 "}
,
		{
			"id" : "63_177",
			"source" : "63",
			"target" : "177",
			"name": "infoD|http(s)",
			"appearances": "1 "}
,
		{
			"id" : "63_178",
			"source" : "63",
			"target" : "178",
			"name": "serD|unassigned",
			"appearances": "9 "}
,
		{
			"id" : "63_179",
			"source" : "63",
			"target" : "179",
			"name": "vulnD|storage",
			"appearances": "2 "}
,
		{
			"id" : "65_181",
			"source" : "65",
			"target" : "181",
			"name": "infoD|http(s)",
			"appearances": "9 "}
,
		{
			"id" : "65_182",
			"source" : "65",
			"target" : "182",
			"name": "CnC|http(s)",
			"appearances": "1 "}
,
		{
			"id" : "67_184",
			"source" : "67",
			"target" : "184",
			"name": "CnC|http(s)",
			"appearances": "1 "}
,
		{
			"id" : "67_185",
			"source" : "67",
			"target" : "185",
			"name": "rPrivEsc|http(s)",
			"appearances": "4 "}
,
		{
			"id" : "87_207",
			"source" : "87",
			"target" : "207",
			"name": "exfil|unassigned",
			"appearances": "1 "}
,
		{
			"id" : "91_210",
			"source" : "91",
			"target" : "210",
			"name": "infoD|http(s)",
			"appearances": "1 "}
,
		{
			"id" : "91_211",
			"source" : "91",
			"target" : "211",
			"name": "serD|unassigned",
			"appearances": "11 "}
,
		{
			"id" : "91_212",
			"source" : "91",
			"target" : "212",
			"name": "hostD|http(s)",
			"appearances": "2 "}
,
		{
			"id" : "91_213",
			"source" : "91",
			"target" : "213",
			"name": "hostD|surveillance",
			"appearances": "1 "}
,
		{
			"id" : "91_214",
			"source" : "91",
			"target" : "214",
			"name": "vulnD|surveillance",
			"appearances": "1 "}
,
		{
			"id" : "91_215",
			"source" : "91",
			"target" : "215",
			"name": "serD|remoteAccess",
			"appearances": "4 "}
,
		{
			"id" : "91_216",
			"source" : "91",
			"target" : "216",
			"name": "hostD|wireless",
			"appearances": "1 "}
,
		{
			"id" : "99_228",
			"source" : "99",
			"target" : "228",
			"name": "vulnD|storage",
			"appearances": "5 "}
,
		{
			"id" : "120_244",
			"source" : "120",
			"target" : "244",
			"name": "infoD|http(s)",
			"appearances": "1 "}
,
		{
			"id" : "120_3",
			"source" : "120",
			"target" : "3",
			"name": "serD|unassigned",
			"appearances": "9 "}
,
		{
			"id" : "120_245",
			"source" : "120",
			"target" : "245",
			"name": "vulnD|storage",
			"appearances": "1 "}
,
		{
			"id" : "120_246",
			"source" : "120",
			"target" : "246",
			"name": "surf|remoteAccess",
			"appearances": "2 "}
,
		{
			"id" : "120_247",
			"source" : "120",
			"target" : "247",
			"name": "infoD|remoteAccess",
			"appearances": "13 "}
,
		{
			"id" : "120_248",
			"source" : "120",
			"target" : "248",
			"name": "serD|remoteAccess",
			"appearances": "13 "}
,
		{
			"id" : "178_306",
			"source" : "178",
			"target" : "306",
			"name": "vulnD|storage",
			"appearances": "8 "}
,
		{
			"id" : "178_307",
			"source" : "178",
			"target" : "307",
			"name": "vulnD|http(s)",
			"appearances": "1 "}
,
		{
			"id" : "181_310",
			"source" : "181",
			"target" : "310",
			"name": "rPrivEsc|http(s)",
			"appearances": "17 "}
,
		{
			"id" : "211_334",
			"source" : "211",
			"target" : "334",
			"name": "vulnD|storage",
			"appearances": "18 "}
,
		{
			"id" : "211_335",
			"source" : "211",
			"target" : "335",
			"name": "hostD|remoteAccess",
			"appearances": "1 "}
,
		{
			"id" : "211_336",
			"source" : "211",
			"target" : "336",
			"name": "hostD|http(s)",
			"appearances": "1 "}
,
		{
			"id" : "211_337",
			"source" : "211",
			"target" : "337",
			"name": "vulnD|remoteAccess",
			"appearances": "1 "}
,
		{
			"id" : "247_371",
			"source" : "247",
			"target" : "371",
			"name": "serD|unassigned",
			"appearances": "4 "}
,
		{
			"id" : "247_372",
			"source" : "247",
			"target" : "372",
			"name": "vulnD|storage",
			"appearances": "1 "}
,
		{
			"id" : "247_120",
			"source" : "247",
			"target" : "120",
			"name": "hostD|remoteAccess",
			"appearances": "9 "}
,
		{
			"id" : "247_373",
			"source" : "247",
			"target" : "373",
			"name": "infoD|remoteAccess",
			"appearances": "8 "}
,
		{
			"id" : "247_374",
			"source" : "247",
			"target" : "374",
			"name": "acctManip|broadcast",
			"appearances": "13 "}
,
		{
			"id" : "248_375",
			"source" : "248",
			"target" : "375",
			"name": "vulnD|storage",
			"appearances": "11 "}
,
		{
			"id" : "248_376",
			"source" : "248",
			"target" : "376",
			"name": "vulnD|voip",
			"appearances": "1 "}
,
		{
			"id" : "306_181",
			"source" : "306",
			"target" : "181",
			"name": "infoD|http(s)",
			"appearances": "8 "}
,
		{
			"id" : "310_428",
			"source" : "310",
			"target" : "428",
			"name": "acctManip|http(s)",
			"appearances": "17 "}
,
		{
			"id" : "334_448",
			"source" : "334",
			"target" : "448",
			"name": "serD|unassigned",
			"appearances": "4 "}
,
		{
			"id" : "334_449",
			"source" : "334",
			"target" : "449",
			"name": "serD|remoteAccess",
			"appearances": "13 "}
,
		{
			"id" : "373_484",
			"source" : "373",
			"target" : "484",
			"name": "hostD|remoteAccess",
			"appearances": "6 "}
,
		{
			"id" : "374_485",
			"source" : "374",
			"target" : "485",
			"name": "netDOS|broadcast",
			"appearances": "13 "}
,
		{
			"id" : "375_247",
			"source" : "375",
			"target" : "247",
			"name": "infoD|remoteAccess",
			"appearances": "11 "}
,
		{
			"id" : "428_522",
			"source" : "428",
			"target" : "522",
			"name": "remoteexp|http(s)",
			"appearances": "17 "}
,
		{
			"id" : "449_211",
			"source" : "449",
			"target" : "211",
			"name": "serD|unassigned",
			"appearances": "10 "}
,
		{
			"id" : "449_533",
			"source" : "449",
			"target" : "533",
			"name": "vulnD|storage",
			"appearances": "2 "}
,
		{
			"id" : "522_594",
			"source" : "522",
			"target" : "594",
			"name": "CnC|http(s)",
			"appearances": "15 "}
,
		{
			"id" : "522_595",
			"source" : "522",
			"target" : "595",
			"name": "ACE|http(s)",
			"appearances": "2 "}
,
		{
			"id" : "594_660",
			"source" : "594",
			"target" : "660",
			"name": "ACE|http(s)",
			"appearances": "15 "}
,
		{
			"id" : "660_716",
			"source" : "660",
			"target" : "716",
			"name": "netDOS|http(s)",
			"appearances": "2 "}
,
		{
			"id" : "660_717",
			"source" : "660",
			"target" : "717",
			"name": "resHJ|http(s)",
			"appearances": "13 "}
,
		{
			"id" : "717_769",
			"source" : "717",
			"target" : "769",
			"name": "dManip|http(s)",
			"appearances": "13 "}
,
		{
			"id" : "769_815",
			"source" : "769",
			"target" : "815",
			"name": "exfil|http(s)",
			"appearances": "13 "}
,
		{
			"id" : "815_850",
			"source" : "815",
			"target" : "850",
			"name": "delivery|http(s)",
			"appearances": "13 "}

	]
}
